Workbook

Sheet Backup
A1: Receive Date | B1: Return Date | C1: Invoice Day | D1: Transaction Type | E1: Quantity | F1: Net Receipts | G1: Net Receipts Currency | H1: List Price | I1: List Price Currency | J1: Rebate In Agreement Currency | K1: Rebate per Units | L1: Price per unit | M1: Agreement Currency | N1: Rebate In Purchase Order Currency | O1: Purchase Order Currency | P1: Purchase Order | Q1: Asin | R1: UPC | S1: EAN | T1: Manufacturer | U1: Distributor | V1: Product Group | W1: Category | X1: Subcategory | Y1: Title | Z1: Product Description | AA1: Binding | AB1: Cost Currency | AC1: Old Cost | AD1: New Cost | AE1: Price Protection Agreement | AF1: Price Protection Day | AG1: Cost Variance | AH1: Invoice | AI1: Multi-Country Parent Agreement ID | AJ1: Invoice Concate
A2: 2022-12-16 | D2: Distributor Shipment | E2: 12 | F2: 1893.12 | G2: EUR | H2: 3137.76 | I2: EUR | J2: 64.36608 | K2: =J2/E2 -> 5.36384 | L2: =F2/E2 -> 157.76 | M2: EUR | N2: 64.36608 | O2: EUR | P2: 4A3KDTEZ | Q2: B079Z3DSBK | S2: 5099206076778 | T2: LOGC8 | U2: L***8 | V2: 147 | W2: 14700900 | X2: 14700939 | Y2: Logitech G X56 H.O.T.A.S Controller Acceleratore e Joystick RGB X56 HOTAS, 6 DoF Gradi di ‎Libertà, 4 Opzioni Tensionamento, +189 Controlli Programmabili, illuminazione RGB, 2x USB, PC ‎‎- Nero | AA2: accessory | AJ2: =P2&Q2 -> 4A3KDTEZB079Z3DSBK
A3: 2022-12-07 | D3: Distributor Shipment | E3: 4 | F3: 335.56 | G3: EUR | H3: 540.96 | I3: EUR | J3: 11.40904 | K3: =J3/E3 -> 2.85226 | L3: =F3/E3 -> 83.89 | M3: EUR | N3: 11.40904 | O3: EUR | P3: 3A946EXY | Q3: B07W6G3KBL | S3: 5099206107090 | T3: LOGC8 | U3: L***8 | V3: 147 | W3: 14700900 | X3: 14700933 | Y3: Logitech G PRO X SUPERLIGHT Mouse Gaming Wireless, Leggero 63 g, Sensore HERO 25K, 25.600 DPI, 5 Tasti Programmabili, Lunga Autonomia, Memoria Integrata, per eSport, PC / Mac - Rosso | AA3: pc | AJ3: =P3&Q3 -> 3A946EXYB07W6G3KBL
A4: 2022-12-21 | D4: Distributor Shipment | E4: 4 | F4: 257.68 | G4: EUR | H4: 377 | I4: EUR | J4: 8.76112 | K4: =J4/E4 -> 2.19028 | L4: =F4/E4 -> 64.42 | M4: EUR | N4: 8.76112 | O4: EUR | P4: 3GBCH66M | Q4: B0055ZWOZ4 | S4: 5099206027183 | T4: LOGC8 | U4: L***8 | V4: 147 | W4: 14700900 | X4: 14700930 | Y4: Logitech K750 Tastiera Solare Wireless per Windows, Layout Spagnolo QWERTY - Nero | AA4: pc | AJ4: =P4&Q4 -> 3GBCH66MB0055ZWOZ4
A5: 2022-12-30 | D5: Distributor Shipment | E5: 8 | F5: 210.96 | G5: EUR | H5: 354 | I5: EUR | J5: 7.17264 | K5: =J5/E5 -> 0.89658 | L5: =F5/E5 -> 26.37 | M5: EUR | N5: 7.17264 | O5: EUR | P5: 7H9X1Z6S | Q5: B00Q6MR0UO | S5: 5099206053830 | T5: LOGC8 | U5: L***8 | V5: 147 | W5: 14700900 | X5: 14700933 | Y5: Logitech G300s Mouse Gaming Ottico, 2.500 DPI, RGB, Design Leggero, 9 Pulsanti ‎ Programmabili, Memoria Integrata, Per Entrambe le Mani, Compatibile con PC/Mac/Laptop, Nero | AA5: accessory | AJ5: =P5&Q5 -> 7H9X1Z6SB00Q6MR0UO
A6: 2022-12-16 | D6: Distributor Shipment | E6: 8 | F6: 324.8 | G6: EUR | H6: 472.08 | I6: EUR | J6: 11.0432 | K6: =J6/E6 -> 1.3804 | L6: =F6/E6 -> 40.6 | M6: EUR | N6: 11.0432 | O6: EUR | P6: 2TMBDXBK | Q6: B07W4DHZLS | S6: 5099206094123 | T6: LOGC8 | U6: L***8 | V6: 147 | W6: 14700900 | X6: 14700930 | Y6: Logitech Keys-To-Go Tastiera Bluetooth, Sottile e Leggera, per iPhone, iPad, Apple TV e tutti i dispositivi iOS, Layout Italiano QWERTY - Rosa | AA6: pc | AJ6: =P6&Q6 -> 2TMBDXBKB07W4DHZLS
A7: 2022-12-27 | D7: Distributor Shipment | E7: 4 | F7: 301.64 | G7: EUR | H7: 442.6 | I7: EUR | J7: 10.25576 | K7: =J7/E7 -> 2.56394 | L7: =F7/E7 -> 75.41 | M7: EUR | N7: 10.25576 | O7: EUR | P7: 4GF112AE | Q7: B07W4DGFSM | S7: 5099206103733 | T7: LOGC8 | U7: L***8 | V7: 147 | W7: 14700900 | X7: 14700933 | Y7: Logitech MX Master 3S - Mouse Wireless ad Alte Prestazioni, Scorrimento Ultraveloce, Ergo, 8K DPI, Tracciamento su Vetro, Clic Silenziosi, USB C, Bluetooth, Windows, Linux, Chrome - Grigio chiaro | AA7: accessory | AJ7: =P7&Q7 -> 4GF112AEB07W4DGFSM
A8: 2022-12-29 | D8: Distributor Shipment | E8: 50 | F8: 468 | G8: EUR | H8: 696.5 | I8: EUR | J8: 15.912 | K8: =J8/E8 -> 0.31824 | L8: =F8/E8 -> 9.36 | M8: EUR | N8: 15.912 | O8: EUR | P8: 4E16R26M | Q8: B003V0QEV0 | S8: 5099206021341 | T8: LOGC8 | U8: L***8 | V8: 147 | W8: 14700900 | X8: 14700930 | Y8: Logitech K120 Tastiera Cablata, Layout ‎Francese Azerty | AA8: pc | AJ8: =P8&Q8 -> 4E16R26MB003V0QEV0
A9: 2022-12-16 | D9: Distributor Shipment | E9: 1 | F9: 210.52 | G9: EUR | H9: 336.06 | I9: EUR | J9: 7.15768 | K9: =J9/E9 -> 7.15768 | L9: =F9/E9 -> 210.52 | M9: EUR | N9: 7.15768 | O9: EUR | P9: 4A3KDTEZ | Q9: B07W6JB7N7 | S9: 5099206082809 | T9: LOGC8 | U9: L***8 | V9: 147 | W9: 14700900 | X9: 14700939 | Y9: Logitech G923 Volante da Corsa e Pedali per PS5, PS4 e PC, UK Inglese Spina di Alimentazione Tipo G, Nero | AA9: pc | AJ9: =P9&Q9 -> 4A3KDTEZB07W6JB7N7
A10: 2022-12-16 | D10: Distributor Shipment | E10: 70 | F10: 655.2 | G10: EUR | H10: 975.1 | I10: EUR | J10: 22.2768 | K10: =J10/E10 -> 0.31824 | L10: =F10/E10 -> 9.36 | M10: EUR | N10: 22.2768 | O10: EUR | P10: 2TMBDXBK | Q10: B01A9GXEOI | R10: 777060019746 | S10: 5099206062856 | T10: LOGC8 | U10: L***8 | V10: 147 | W10: 14700900 | X10: 14700933 | Y10: Logitech M171 Mouse Wireless, 2.4 GHz con Mini Ricevitore USB, Rilevamento Ottico, Durata ‎Batteria Fino a 12 Mesi, Mouse Ambidestro per PC/Mac/Laptop, Nero | AA10: accessory | AJ10: =P10&Q10 -> 2TMBDXBKB01A9GXEOI
A11: 2022-12-17 | D11: Distributor Shipment | E11: 60 | F11: 1867.2 | G11: EUR | H11: 2360.4 | I11: EUR | J11: 63.4848 | K11: =J11/E11 -> 1.05808 | L11: =F11/E11 -> 31.12 | M11: EUR | N11: 63.4848 | O11: EUR | P11: 2W68T8TO | Q11: B07W5JKBMG | S11: 5099206093867 | T11: LOGC8 | U11: L***8 | V11: 147 | W11: 14701000 | X11: 14701080 | Y11: ASTRO Gaming Adattatore HDMI per PS5, Estrattore Audio HDMI 4K a Ottico TOSLINK SPDIF, Compatibile con Stazione Base A50, Auricolare con Microfono A20 per Giochi PlayStation 5 | AA11: consumer_electronics | AJ11: =P11&Q11 -> 2W68T8TOB07W5JKBMG
A12: 2022-12-06 | D12: Distributor Shipment | E12: 12 | F12: 1455 | G12: EUR | H12: 2055.6 | I12: EUR | J12: 49.47 | K12: =J12/E12 -> 4.1225 | L12: =F12/E12 -> 121.25 | M12: EUR | N12: 49.47 | O12: EUR | P12: 7EMS2FPG | Q12: B074KGS5C3 | S12: 5099206072800 | T12: LOGC8 | U12: L***8 | V12: 147 | W12: 14700900 | X12: 14700930 | Y12: Logitech Craft Tastiera, Layout Tedesco ‎Qwertz | AA12: accessory | AJ12: =P12&Q12 -> 7EMS2FPGB074KGS5C3
A13: 2022-12-29 | D13: Distributor Shipment | E13: 276 | F13: 7278.12 | G13: EUR | H13: 12213 | I13: EUR | J13: 247.45608 | K13: =J13/E13 -> 0.89658 | L13: =F13/E13 -> 26.37 | M13: EUR | N13: 247.45608 | O13: EUR | P13: 7H9X1Z6S | Q13: B00Q6MR0UO | S13: 5099206053830 | T13: LOGC8 | U13: L***8 | V13: 147 | W13: 14700900 | X13: 14700933 | Y13: Logitech G300s Mouse Gaming Ottico, 2.500 DPI, RGB, Design Leggero, 9 Pulsanti ‎ Programmabili, Memoria Integrata, Per Entrambe le Mani, Compatibile con PC/Mac/Laptop, Nero | AA13: accessory | AJ13: =P13&Q13 -> 7H9X1Z6SB00Q6MR0UO
A14: 2022-12-22 | D14: Distributor Shipment | E14: 40 | F14: 655.6 | G14: EUR | H14: 983.2 | I14: EUR | J14: 22.2904 | K14: =J14/E14 -> 0.55726 | L14: =F14/E14 -> 16.39 | M14: EUR | N14: 22.2904 | O14: EUR | P14: 2M7QFTCO | Q14: B07W7JYP91 | S14: 5099206085695 | T14: LOGC8 | U14: L***8 | V14: 147 | W14: 14700900 | X14: 14700933 | Y14: Logitech Pebble Mouse Wireless, Bluetooth o 2,4 GHz con Mini Ricevitore USB, Silenzioso, Mouse per ‎Computer Sottile, Clic silenziosi, per PC/Mac/Laptop/iPadOS/Chromebook - Verde | AA14: pc | AJ14: =P14&Q14 -> 2M7QFTCOB07W7JYP91
A15: 2022-12-06 | D15: Distributor Shipment | E15: 24 | F15: 278.4 | G15: EUR | H15: 471.84 | I15: EUR | J15: 9.4656 | K15: =J15/E15 -> 0.3944 | L15: =F15/E15 -> 11.6 | M15: EUR | N15: 9.4656 | O15: EUR | P15: 2CLMXQWQ | Q15: B07W7K29YK | S15: 5099206104389 | T15: LOGC8 | U15: L***8 | V15: 147 | W15: 14700900 | X15: 14700933 | Y15: Logitech G G440 Gaming Mouse Pad Rigido, Ottimizzato per i Sensori da Gioco, Attrito Moderato, Antiscivolo, Accessori da Gioco per Mac e PC, 340 x 280 x 5 mm | AA15: consumer_electronics | AJ15: =P15&Q15 -> 2CLMXQWQB07W7K29YK
A16: 2022-12-23 | D16: Distributor Shipment | E16: 4 | F16: 105.48 | G16: EUR | H16: 177 | I16: EUR | J16: 3.58632 | K16: =J16/E16 -> 0.89658 | L16: =F16/E16 -> 26.37 | M16: EUR | N16: 3.58632 | O16: EUR | P16: 7H9X1Z6S | Q16: B00Q6MR0UO | S16: 5099206053830 | T16: LOGC8 | U16: L***8 | V16: 147 | W16: 14700900 | X16: 14700933 | Y16: Logitech G300s Mouse Gaming Ottico, 2.500 DPI, RGB, Design Leggero, 9 Pulsanti ‎ Programmabili, Memoria Integrata, Per Entrambe le Mani, Compatibile con PC/Mac/Laptop, Nero | AA16: accessory | AJ16: =P16&Q16 -> 7H9X1Z6SB00Q6MR0UO
A17: 2022-12-06 | D17: Distributor Shipment | E17: 10 | F17: 322.1 | G17: EUR | H17: 483.5 | I17: EUR | J17: 10.9514 | K17: =J17/E17 -> 1.09514 | L17: =F17/E17 -> 32.21 | M17: EUR | N17: 10.9514 | O17: EUR | P17: 3A946EXY | Q17: B015BCWNNS | S17: 5099206059481 | T17: LOGC8 | U17: L***8 | V17: 147 | W17: 14700900 | X17: 14700930 | Y17: Logitech K400 PLUS Tastiera Wireless, Layout Ceco-Slovacco Qwerty, Nero | AA17: pc | AJ17: =P17&Q17 -> 3A946EXYB015BCWNNS
A18: 2022-12-29 | D18: Distributor Shipment | E18: 6 | F18: 158.1 | G18: EUR | H18: 236.04 | I18: EUR | J18: 5.3754 | K18: =J18/E18 -> 0.8959 | L18: =F18/E18 -> 26.35 | M18: EUR | N18: 5.3754 | O18: EUR | P18: 243WWSUA | Q18: B00DN1D1MW | S18: 5099206039148 | T18: LOGC8 | U18: L***8 | V18: 147 | W18: 14700900 | X18: 14700930 | Y18: Logitech MK270 Combo Tastiera e Mouse Wireless per Windows, Layout Internazionale QWERTY - Nero | AA18: pc | AJ18: =P18&Q18 -> 243WWSUAB00DN1D1MW
A19: 2022-12-13 | D19: Distributor Shipment | E19: 30 | F19: 280.8 | G19: EUR | H19: 417.9 | I19: EUR | J19: 9.5472 | K19: =J19/E19 -> 0.31824 | L19: =F19/E19 -> 9.36 | M19: EUR | N19: 9.5472 | O19: EUR | P19: 31DJDC7Q | Q19: B01A9GXEOI | R19: 777060019746 | S19: 5099206062856 | T19: LOGC8 | U19: L***8 | V19: 147 | W19: 14700900 | X19: 14700933 | Y19: Logitech M171 Mouse Wireless, 2.4 GHz con Mini Ricevitore USB, Rilevamento Ottico, Durata ‎Batteria Fino a 12 Mesi, Mouse Ambidestro per PC/Mac/Laptop, Nero | AA19: accessory | AJ19: =P19&Q19 -> 31DJDC7QB01A9GXEOI
A20: 2022-12-22 | D20: Distributor Shipment | E20: 16 | F20: 379.84 | G20: EUR | H20: 629.44 | I20: EUR | J20: 12.91456 | K20: =J20/E20 -> 0.80716 | L20: =F20/E20 -> 23.74 | M20: EUR | N20: 12.91456 | O20: EUR | P20: 5MWU8WTD | Q20: B07W6HBBMH | S20: 5099206104303 | T20: LOGC8 | U20: L***8 | V20: 147 | W20: 14700900 | X20: 14700933 | Y20: Logitech G G840 Gaming Mouse Pad XL, Ottimizzato per i Sensori da Gioco, Attrito Moderato, Antiscivolo, Accessori da Gioco per Mac e PC, 900 x 400 x 3 mm | AA20: consumer_electronics | AJ20: =P20&Q20 -> 5MWU8WTDB07W6HBBMH
A21: 2022-12-06 | D21: Distributor Shipment | E21: 48 | F21: 5568.96 | G21: EUR | H21: 7868.64 | I21: EUR | J21: 189.34464 | K21: =J21/E21 -> 3.94468 | L21: =F21/E21 -> 116.02 | M21: EUR | N21: 189.34464 | O21: EUR | P21: 2CLMXQWQ | Q21: B07W6HPP3R | S21: 5099206096134 | T21: LOGC8 | U21: L***8 | V21: 147 | W21: 14700900 | X21: 14700930 | Y21: Logitech Combo Touch Custodia con Tastiera per iPad Air (4 e 5 gen - 2020, 2022), Layout UK/US QWERTY - Grigio | AA21: pc | AJ21: =P21&Q21 -> 2CLMXQWQB07W6HPP3R
A22: 2022-12-19 | D22: Distributor Shipment | E22: 16 | F22: 328 | G22: EUR | H22: 655.04 | I22: EUR | J22: 11.152 | K22: =J22/E22 -> 0.697 | L22: =F22/E22 -> 20.5 | M22: EUR | N22: 11.152 | O22: EUR | P22: 7RAC5F9E | Q22: B002L3TSLQ | R22: 758399157934 | S22: 3610480106092 | T22: LOGC8 | U22: L***8 | V22: 147 | W22: 14700900 | X22: 14700930 | Y22: Logitech R400 Puntatore Laser per Presentazioni Wireless, 2.4 GHz e Bluetooth, Ricevitore USB, ‎Puntatore Laser Rosso, Portata 15 m, 6 Pulsanti, Controllo Intuitivo, Indicatore ‎Batteria, PC, Nero | AA22: consumer_electronics | AJ22: =P22&Q22 -> 7RAC5F9EB002L3TSLQ
A23: 2022-12-16 | D23: Distributor Shipment | E23: 176 | F23: 7145.6 | G23: EUR | H23: 10385.76 | I23: EUR | J23: 242.9504 | K23: =J23/E23 -> 1.3804 | L23: =F23/E23 -> 40.6 | M23: EUR | N23: 242.9504 | O23: EUR | P23: 36BT7GGL | Q23: B00O8K42PM | S23: 5099206055490 | T23: LOGC8 | U23: L***8 | V23: 147 | W23: 14700900 | X23: 14700930 | Y23: Logitech Keys-To-Go Tastiera Bluetooth, Layout Spagnolo QWERTY - Nero | AA23: accessory | AJ23: =P23&Q23 -> 36BT7GGLB00O8K42PM
A24: 2022-12-16 | D24: Distributor Shipment | E24: 336 | F24: 6888 | G24: EUR | H24: 13755.84 | I24: EUR | J24: 234.192 | K24: =J24/E24 -> 0.697 | L24: =F24/E24 -> 20.5 | M24: EUR | N24: 234.192 | O24: EUR | P24: 7RAC5F9E | Q24: B002L3TSLQ | R24: 758399157934 | S24: 3610480106092 | T24: LOGC8 | U24: L***8 | V24: 147 | W24: 14700900 | X24: 14700930 | Y24: Logitech R400 Puntatore Laser per Presentazioni Wireless, 2.4 GHz e Bluetooth, Ricevitore USB, ‎Puntatore Laser Rosso, Portata 15 m, 6 Pulsanti, Controllo Intuitivo, Indicatore ‎Batteria, PC, Nero | AA24: consumer_electronics | AJ24: =P24&Q24 -> 7RAC5F9EB002L3TSLQ
A25: 2022-12-16 | D25: Distributor Shipment | E25: 80 | F25: 656 | G25: EUR | H25: 983.2 | I25: EUR | J25: 22.304 | K25: =J25/E25 -> 0.2788 | L25: =F25/E25 -> 8.2 | M25: EUR | N25: 22.304 | O25: EUR | P25: 3UDP1VLY | Q25: B07W6JKH17 | S25: 5099206091627 | T25: LOGC8 | U25: L***8 | V25: 147 | W25: 14700900 | X25: 14700933 | Y25: Logitech USB Unifying Receiver - Nero | AA25: consumer_electronics | AJ25: =P25&Q25 -> 3UDP1VLYB07W6JKH17
A26: 2022-12-13 | D26: Distributor Shipment | E26: 16 | F26: 1648.96 | G26: EUR | H26: 2164 | I26: EUR | J26: 56.06464 | K26: =J26/E26 -> 3.50404 | L26: =F26/E26 -> 103.06 | M26: EUR | N26: 56.06464 | O26: EUR | P26: 56UO2L2I | Q26: B07PPNT9B2 | S26: 5099206082977 | T26: LOGC8 | U26: L***8 | V26: 147 | W26: 14700900 | X26: 14700939 | Y26: ASTRO Gaming MixAmp Pro TR Amplificatore per Headset da Gaming, 4° Generazione, Dolby Audio, Funzionalità Scheda Audio USB, Digital Daisy-Chain, per PS5, PS4, PC, Mac, Nintendo Switch, Nero / Blu | AA26: pc | AJ26: =P26&Q26 -> 56UO2L2IB07PPNT9B2
A27: 2022-12-30 | D27: Distributor Shipment | E27: 176 | F27: 12907.84 | G27: EUR | H27: 20917.6 | I27: EUR | J27: 438.86656 | K27: =J27/E27 -> 2.49356 | L27: =F27/E27 -> 73.34 | M27: EUR | N27: 438.86656 | O27: EUR | P27: 7H9X1Z6S | Q27: B07W6JNQ82 | S27: 5099206086425 | T27: LOGC8 | U27: L***8 | V27: 147 | W27: 14700900 | X27: 14700930 | Y27: Logitech G PRO TKL Tastiera Gaming Meccanica, GX Blue Clicky Switch, LIGHTSYNC RGB, Design Portatile Tenkeyless, Pensato per Esport Gaming, Micro Cavo USB Rimovibile, QWERTY US Layout, Nero | AA27: pc | AJ27: =P27&Q27 -> 7H9X1Z6SB07W6JNQ82
A28: 2022-12-06 | D28: Distributor Shipment | E28: 4 | F28: 387.32 | G28: EUR | H28: 459 | I28: EUR | J28: 13.16888 | K28: =J28/E28 -> 3.29222 | L28: =F28/E28 -> 96.83 | M28: EUR | N28: 13.16888 | O28: EUR | P28: 5FPQ9KSZ | Q28: B07W4DHL8V | S28: 5099206106222 | T28: LOGC8 | U28: L***8 | V28: 267 | W28: 26704000 | X28: 26704200 | Y28: Logitech G Blue Yeti Kit Game Streaming con Microfono Gaming USB Yeti, Software Blue VO!CE, Temi Esclusivi Streamlabs, Filtro Pop Blu Personalizzato, PC/Mac/PS4/PS5 - Nero | AA28: consumer_electronics | AJ28: =P28&Q28 -> 5FPQ9KSZB07W4DHL8V
A29: 2022-12-22 | D29: Distributor Shipment | E29: 76 | F29: 5731.16 | G29: EUR | H29: 8409.4 | I29: EUR | J29: 194.85944 | K29: =J29/E29 -> 2.56394 | L29: =F29/E29 -> 75.41 | M29: EUR | N29: 194.85944 | O29: EUR | P29: 4GF112AE | Q29: B07W4DGFSM | S29: 5099206103733 | T29: LOGC8 | U29: L***8 | V29: 147 | W29: 14700900 | X29: 14700933 | Y29: Logitech MX Master 3S - Mouse Wireless ad Alte Prestazioni, Scorrimento Ultraveloce, Ergo, 8K DPI, Tracciamento su Vetro, Clic Silenziosi, USB C, Bluetooth, Windows, Linux, Chrome - Grigio chiaro | AA29: accessory | AJ29: =P29&Q29 -> 4GF112AEB07W4DGFSM
A30: 2022-12-13 | D30: Distributor Shipment | E30: 10 | F30: 175.6 | G30: EUR | H30: 270.4 | I30: EUR | J30: 5.9704 | K30: =J30/E30 -> 0.59704 | L30: =F30/E30 -> 17.56 | M30: EUR | N30: 5.9704 | O30: EUR | P30: 1KW92RHQ | Q30: B0042BVWZ0 | S30: 5099206020634 | T30: LOGC8 | U30: L***8 | V30: 147 | W30: 14700900 | X30: 14700930 | Y30: Logitech MK120 Kit Tastiera e Mouse Cablati, Layout Svizzero ‎Qwertz, Nero | AA30: pc | AJ30: =P30&Q30 -> 1KW92RHQB0042BVWZ0
A31: 2022-12-17 | D31: Distributor Shipment | E31: 4 | F31: 189.92 | G31: EUR | H31: 311.44 | I31: EUR | J31: 6.45728 | K31: =J31/E31 -> 1.61432 | L31: =F31/E31 -> 47.48 | M31: EUR | N31: 6.45728 | O31: EUR | P31: 8FQ2THMT | Q31: B07W7MQMDH | S31: 5099206101821 | T31: LOGC8 | U31: L***8 | V31: 147 | W31: 14700900 | X31: 14700930 | Y31: Logitech G413 SE Tastiera Meccanica Gaming Full Size - Tastiera Retroilluminata con Switch Meccanici Tattili, Anti-Ghosting, Compatibile con Windows, macOS, Layout Italiano QWERTY - Alluminio Nero | AA31: pc | AJ31: =P31&Q31 -> 8FQ2THMTB07W7MQMDH
A32: 2022-12-20 | D32: Distributor Shipment | E32: 20 | F32: 327.8 | G32: EUR | H32: 491.6 | I32: EUR | J32: 11.1452 | K32: =J32/E32 -> 0.55726 | L32: =F32/E32 -> 16.39 | M32: EUR | N32: 11.1452 | O32: EUR | P32: 7RAC5F9E | Q32: B01K7GEG9W | R32: 097855123381 | S32: 5099206066199 | T32: LOGC8 | U32: L***8 | V32: 147 | W32: 14700900 | X32: 14700933 | Y32: Logitech M220 SILENT Mouse Wireless, 2,4 GHz con Ricevitore USB, Tracciamento Ottico 1000 DPI, Durata Batteria di 18 Mesi, Ambidestro, Compatibile con PC, Mac, Laptop - Grigio | AA32: accessory | AJ32: =P32&Q32 -> 7RAC5F9EB01K7GEG9W
A33: 2022-12-13 | D33: Distributor Shipment | E33: 50 | F33: 468 | G33: EUR | H33: 696.5 | I33: EUR | J33: 15.912 | K33: =J33/E33 -> 0.31824 | L33: =F33/E33 -> 9.36 | M33: EUR | N33: 15.912 | O33: EUR | P33: 31QWZ6KB | Q33: B01A9GXEOI | R33: 777060019746 | S33: 5099206062856 | T33: LOGC8 | U33: L***8 | V33: 147 | W33: 14700900 | X33: 14700933 | Y33: Logitech M171 Mouse Wireless, 2.4 GHz con Mini Ricevitore USB, Rilevamento Ottico, Durata ‎Batteria Fino a 12 Mesi, Mouse Ambidestro per PC/Mac/Laptop, Nero | AA33: accessory | AJ33: =P33&Q33 -> 31QWZ6KBB01A9GXEOI
A34: 2022-12-16 | D34: Distributor Shipment | E34: 16 | F34: 1113.76 | G34: EUR | H34: 1691.84 | I34: EUR | J34: 37.86784 | K34: =J34/E34 -> 2.36674 | L34: =F34/E34 -> 69.61 | M34: EUR | N34: 37.86784 | O34: EUR | P34: 2R6FMUZD | Q34: B07W4DH65R | S34: 5099206107489 | T34: LOGC8 | U34: L***8 | V34: 147 | W34: 14700900 | X34: 14700930 | Y34: Logitech per iPad (10ª generazione) Custodia con tastiera | Slim Folio con tastiera wireless integrata (grafite) - English Layout | AA34: pc | AJ34: =P34&Q34 -> 2R6FMUZDB07W4DH65R
A35: 2022-12-29 | D35: Distributor Shipment | E35: 2870 | F35: 47039.3 | G35: EUR | H35: 70544.6 | I35: EUR | J35: 1599.3362 | K35: =J35/E35 -> 0.55726 | L35: =F35/E35 -> 16.39 | M35: EUR | N35: 1599.3362 | O35: EUR | P35: 2LZI7R4T | Q35: B077BT728N | S35: 5099206076679 | T35: LOGC8 | U35: L***8 | V35: 147 | W35: 14700900 | X35: 14700930 | Y35: Logitech K280e Pro Tastiera, Layout Tedesco ‎QWERTZ, Nero | AA35: pc | AJ35: =P35&Q35 -> 2LZI7R4TB077BT728N
A36: 2022-12-24 | D36: Distributor Shipment | E36: 8 | F36: 603.28 | G36: EUR | H36: 885.2 | I36: EUR | J36: 20.51152 | K36: =J36/E36 -> 2.56394 | L36: =F36/E36 -> 75.41 | M36: EUR | N36: 20.51152 | O36: EUR | P36: 4GF112AE | Q36: B07W4DGFSM | S36: 5099206103733 | T36: LOGC8 | U36: L***8 | V36: 147 | W36: 14700900 | X36: 14700933 | Y36: Logitech MX Master 3S - Mouse Wireless ad Alte Prestazioni, Scorrimento Ultraveloce, Ergo, 8K DPI, Tracciamento su Vetro, Clic Silenziosi, USB C, Bluetooth, Windows, Linux, Chrome - Grigio chiaro | AA36: accessory | AJ36: =P36&Q36 -> 4GF112AEB07W4DGFSM
A37: 2022-12-23 | D37: Distributor Shipment | E37: 4 | F37: 301.64 | G37: EUR | H37: 442.6 | I37: EUR | J37: 10.25576 | K37: =J37/E37 -> 2.56394 | L37: =F37/E37 -> 75.41 | M37: EUR | N37: 10.25576 | O37: EUR | P37: 4GF112AE | Q37: B07W4DGFSM | S37: 5099206103733 | T37: LOGC8 | U37: L***8 | V37: 147 | W37: 14700900 | X37: 14700933 | Y37: Logitech MX Master 3S - Mouse Wireless ad Alte Prestazioni, Scorrimento Ultraveloce, Ergo, 8K DPI, Tracciamento su Vetro, Clic Silenziosi, USB C, Bluetooth, Windows, Linux, Chrome - Grigio chiaro | AA37: accessory | AJ37: =P37&Q37 -> 4GF112AEB07W4DGFSM
A38: 2022-12-30 | D38: Distributor Shipment | E38: 24 | F38: 696.24 | G38: EUR | H38: 1160.4 | I38: EUR | J38: 23.67216 | K38: =J38/E38 -> 0.98634 | L38: =F38/E38 -> 29.01 | M38: EUR | N38: 23.67216 | O38: EUR | P38: 4F3XMHTV | Q38: B0766JZ8Q3 | S38: 5099206074552 | T38: LOGC8 | U38: L***8 | V38: 147 | W38: 22903000 | X38: 14700933 | Y38: Logitech G840 XL Tappetino Mouse Gaming in Tessuto, Mouse Pad 400x900 mm, Spessore 3 mm, Superficie Orientata alle Prestazioni, Basso Attrito, Solida Base in Gomma, Portatile, Nero | AA38: pc | AJ38: =P38&Q38 -> 4F3XMHTVB0766JZ8Q3
A39: 2022-12-22 | D39: Distributor Shipment | E39: 50 | F39: 468 | G39: EUR | H39: 696.5 | I39: EUR | J39: 15.912 | K39: =J39/E39 -> 0.31824 | L39: =F39/E39 -> 9.36 | M39: EUR | N39: 15.912 | O39: EUR | P39: 5MWU8WTD | Q39: B01A9HC69G | R39: 097855119230 | S39: 0097855119230 | T39: LOGC8 | U39: L***8 | V39: 147 | W39: 14700900 | X39: 14700933 | Y39: Logitech M171 Mouse Wireless, 2.4 GHz con Mini Ricevitore USB, Rilevamento Ottico, Durata ‎Batteria 12 Mesi, Mouse Ambidestro per PC/Mac/Laptop, Blu | AA39: accessory | AJ39: =P39&Q39 -> 5MWU8WTDB01A9HC69G
A40: 2022-12-06 | D40: Distributor Shipment | E40: 8 | F40: 882.16 | G40: EUR | H40: 1832 | I40: EUR | J40: 29.99344 | K40: =J40/E40 -> 3.74918 | L40: =F40/E40 -> 110.27 | M40: EUR | N40: 29.99344 | O40: EUR | P40: 1M3XYEGX | Q40: B07W7MSGPL | S40: 5099206082618 | T40: LOGC8 | U40: L***8 | V40: 23 | W40: 2305600 | X40: 2305630 | Y40: Logitech G Tastiera meccanica da gioco 815, Clicky GL con profilo piatto, LIGHTSYNC RGB, design sottile, 5 tasti G programmabili, comandi multimediali, layout tedesco QWERTZ | AA40: pc | AJ40: =P40&Q40 -> 1M3XYEGXB07W7MSGPL
A41: 2022-12-22 | D41: Distributor Shipment | E41: 32 | F41: 1030.72 | G41: EUR | H41: 1547.2 | I41: EUR | J41: 35.04448 | K41: =J41/E41 -> 1.09514 | L41: =F41/E41 -> 32.21 | M41: EUR | N41: 35.04448 | O41: EUR | P41: 4GF112AE | Q41: B07W5JKPFG | S41: 5099206104808 | T41: LOGC8 | U41: L***8 | V41: 147 | W41: 14700900 | X41: 14700930 | Y41: Logitech K380 Tastiera Wireless Bluetooth Multidispositivo, Fino 3 Dispositivi, Compatta,Batteria di 2 Anni - PC, Laptop, Windows, Mac, Chrome OS, Android, iPadOS, Apple TV - Viola | AA41: pc | AJ41: =P41&Q41 -> 4GF112AEB07W5JKPFG
A42: 2022-12-24 | D42: Distributor Shipment | E42: 0 | F42: 0 | G42: EUR | H42: 0 | I42: EUR | J42: 0 | K42: =J42/E42 -> #DIV/0! | L42: =F42/E42 -> #DIV/0! | M42: EUR | N42: 0 | O42: EUR | P42: 7RAC5F9E | Q42: B01K7GEG9W | R42: 097855123381 | S42: 5099206066199 | T42: LOGC8 | U42: L***8 | V42: 147 | W42: 14700900 | X42: 14700933 | Y42: Logitech M220 SILENT Mouse Wireless, 2,4 GHz con Ricevitore USB, Tracciamento Ottico 1000 DPI, Durata Batteria di 18 Mesi, Ambidestro, Compatibile con PC, Mac, Laptop - Grigio | AA42: accessory | AJ42: =P42&Q42 -> 7RAC5F9EB01K7GEG9W
A43: 2022-12-23 | D43: Distributor Shipment | E43: 0 | F43: 0 | G43: EUR | H43: 0 | I43: EUR | J43: 0 | K43: =J43/E43 -> #DIV/0! | L43: =F43/E43 -> #DIV/0! | M43: EUR | N43: 0 | O43: EUR | P43: 7RAC5F9E | Q43: B01K7GEG9W | R43: 097855123381 | S43: 5099206066199 | T43: LOGC8 | U43: L***8 | V43: 147 | W43: 14700900 | X43: 14700933 | Y43: Logitech M220 SILENT Mouse Wireless, 2,4 GHz con Ricevitore USB, Tracciamento Ottico 1000 DPI, Durata Batteria di 18 Mesi, Ambidestro, Compatibile con PC, Mac, Laptop - Grigio | AA43: accessory | AJ43: =P43&Q43 -> 7RAC5F9EB01K7GEG9W
A44: 2022-12-07 | D44: Distributor Shipment | E44: 4 | F44: 420 | G44: EUR | H44: 704.92 | I44: EUR | J44: 14.28 | K44: =J44/E44 -> 3.57 | L44: =F44/E44 -> 105 | M44: EUR | N44: 14.28 | O44: EUR | P44: 5X1OU9ZG | Q44: B07MTY7N22 | S44: 5099206081918 | T44: LOGC8 | U44: L***8 | V44: 147 | W44: 14700900 | X44: 14700939 | Y44: Logitech G935 Cuffie Gaming Wireless RGB, Audio Surround 7.1, Cuffie DTS X 2.0, Driver Pro-G da 50 mm, Wireless 2,4 GHz, Microfono Rocker, PC/Mac/PS4/Nintendo Switch, Nero | AA44: consumer_electronics | AJ44: =P44&Q44 -> 5X1OU9ZGB07MTY7N22
A45: 2022-12-06 | D45: Distributor Shipment | E45: 48 | F45: 5040 | G45: EUR | H45: 8459.04 | I45: EUR | J45: 171.36 | K45: =J45/E45 -> 3.57 | L45: =F45/E45 -> 105 | M45: EUR | N45: 171.36 | O45: EUR | P45: 5X1OU9ZG | Q45: B07MTY7N22 | S45: 5099206081918 | T45: LOGC8 | U45: L***8 | V45: 147 | W45: 14700900 | X45: 14700939 | Y45: Logitech G935 Cuffie Gaming Wireless RGB, Audio Surround 7.1, Cuffie DTS X 2.0, Driver Pro-G da 50 mm, Wireless 2,4 GHz, Microfono Rocker, PC/Mac/PS4/Nintendo Switch, Nero | AA45: consumer_electronics | AJ45: =P45&Q45 -> 5X1OU9ZGB07MTY7N22
A46: 2022-12-21 | D46: Distributor Shipment | E46: 4 | F46: 230.04 | G46: EUR | H46: 340.96 | I46: EUR | J46: 7.82136 | K46: =J46/E46 -> 1.95534 | L46: =F46/E46 -> 57.51 | M46: EUR | N46: 7.82136 | O46: EUR | P46: 3GBCH66M | Q46: B06XPHQW6G | S46: 5099206071711 | T46: LOGC8 | U46: L***8 | V46: 147 | W46: 14700900 | X46: 14700939 | Y46: Logitech G413 Tastiera per Giochi Meccanica, Layout Tedesco, Argento (Silver) | AA46: accessory | AJ46: =P46&Q46 -> 3GBCH66MB06XPHQW6G
A47: 2022-12-13 | D47: Distributor Shipment | E47: 64 | F47: 7480.96 | G47: EUR | H47: 9390.08 | I47: EUR | J47: 254.35264 | K47: =J47/E47 -> 3.97426 | L47: =F47/E47 -> 116.89 | M47: EUR | N47: 254.35264 | O47: EUR | P47: 39TAD6PC | Q47: B07PMKHMFS | S47: 5099206084261 | T47: LOGC8 | U47: L***8 | V47: 147 | W47: 14700900 | X47: 14700939 | Y47: ASTRO Gaming A40 TR Cuffie Gaming Cablate, ASTRO Audio V2, Dolby ATMOS, Jack Audio 3,5 mm, Microfono Intercambiabile, per Xbox Series X|S/Xbox One/PC/Mac/Mobile/Plasystation, Nero/Rosso | AA47: pc | AJ47: =P47&Q47 -> 39TAD6PCB07PMKHMFS
A48: 2022-12-22 | D48: Distributor Shipment | E48: 68 | F48: 4987.12 | G48: EUR | H48: 8081.8 | I48: EUR | J48: 169.56208 | K48: =J48/E48 -> 2.49356 | L48: =F48/E48 -> 73.34 | M48: EUR | N48: 169.56208 | O48: EUR | P48: 1MDL1DPE | Q48: B073399S1L | S48: 5099206074576 | T48: LOGC8 | U48: L***8 | V48: 147 | W48: 14700900 | X48: 14700939 | Y48: Logitech G POWERPLAY Ricarica Wireless Tappetino Mouse, Tappetino per Mouse Gaming in Tessuto o Rigido, Mouse Pad Compatibile con G502 LIGHTSPEED, G PRO Wireless & SUPERLIGHT, G903, G703 | AA48: pc | AJ48: =P48&Q48 -> 1MDL1DPEB073399S1L
A49: 2022-12-19 | D49: Distributor Shipment | E49: 40 | F49: 655.6 | G49: EUR | H49: 983.2 | I49: EUR | J49: 22.2904 | K49: =J49/E49 -> 0.55726 | L49: =F49/E49 -> 16.39 | M49: EUR | N49: 22.2904 | O49: EUR | P49: 7RAC5F9E | Q49: B01K7GEG9W | R49: 097855123381 | S49: 5099206066199 | T49: LOGC8 | U49: L***8 | V49: 147 | W49: 14700900 | X49: 14700933 | Y49: Logitech M220 SILENT Mouse Wireless, 2,4 GHz con Ricevitore USB, Tracciamento Ottico 1000 DPI, Durata Batteria di 18 Mesi, Ambidestro, Compatibile con PC, Mac, Laptop - Grigio | AA49: accessory | AJ49: =P49&Q49 -> 7RAC5F9EB01K7GEG9W
A50: 2022-12-16 | D50: Distributor Shipment | E50: 400 | F50: 6556 | G50: EUR | H50: 9832 | I50: EUR | J50: 222.904 | K50: =J50/E50 -> 0.55726 | L50: =F50/E50 -> 16.39 | M50: EUR | N50: 222.904 | O50: EUR | P50: 7RAC5F9E | Q50: B01K7GEG9W | R50: 097855123381 | S50: 5099206066199 | T50: LOGC8 | U50: L***8 | V50: 147 | W50: 14700900 | X50: 14700933 | Y50: Logitech M220 SILENT Mouse Wireless, 2,4 GHz con Ricevitore USB, Tracciamento Ottico 1000 DPI, Durata Batteria di 18 Mesi, Ambidestro, Compatibile con PC, Mac, Laptop - Grigio | AA50: accessory | AJ50: =P50&Q50 -> 7RAC5F9EB01K7GEG9W
A51: 2022-12-16 | D51: Distributor Shipment | E51: 20 | F51: 327.8 | G51: EUR | H51: 491.6 | I51: EUR | J51: 11.1452 | K51: =J51/E51 -> 0.55726 | L51: =F51/E51 -> 16.39 | M51: EUR | N51: 11.1452 | O51: EUR | P51: 36BT7GGL | Q51: B07W7JYP91 | S51: 5099206085695 | T51: LOGC8 | U51: L***8 | V51: 147 | W51: 14700900 | X51: 14700933 | Y51: Logitech Pebble Mouse Wireless, Bluetooth o 2,4 GHz con Mini Ricevitore USB, Silenzioso, Mouse per ‎Computer Sottile, Clic silenziosi, per PC/Mac/Laptop/iPadOS/Chromebook - Verde | AA51: pc | AJ51: =P51&Q51 -> 36BT7GGLB07W7JYP91
A52: 2022-12-09 | D52: Distributor Shipment | E52: 8 | F52: 257.68 | G52: EUR | H52: 386.8 | I52: EUR | J52: 8.76112 | K52: =J52/E52 -> 1.09514 | L52: =F52/E52 -> 32.21 | M52: EUR | N52: 8.76112 | O52: EUR | P52: 7ILTX3HJ | Q52: B07W7K1LSC | S52: 5099206105706 | T52: LOGC8 | U52: L***8 | V52: 147 | W52: 14700900 | X52: 14700930 | Y52: Logitech Signature K650, Tastiera Poggiapolsi Wireless Full-size con Bluetooth BLE o Ricevitore USB Logi Bolt, Tasti Smorzati e Tastierino, Compatibile con PC/Windows/Mac, Italiano QWERTY - Bianco | AA52: pc | AJ52: =P52&Q52 -> 7ILTX3HJB07W7K1LSC
A53: 2022-12-18 | D53: Distributor Shipment | E53: 10 | F53: 163.9 | G53: EUR | H53: 245.8 | I53: EUR | J53: 5.5726 | K53: =J53/E53 -> 0.55726 | L53: =F53/E53 -> 16.39 | M53: EUR | N53: 5.5726 | O53: EUR | P53: 7RAC5F9E | Q53: B01K7GEG9W | R53: 097855123381 | S53: 5099206066199 | T53: LOGC8 | U53: L***8 | V53: 147 | W53: 14700900 | X53: 14700933 | Y53: Logitech M220 SILENT Mouse Wireless, 2,4 GHz con Ricevitore USB, Tracciamento Ottico 1000 DPI, Durata Batteria di 18 Mesi, Ambidestro, Compatibile con PC, Mac, Laptop - Grigio | AA53: accessory | AJ53: =P53&Q53 -> 7RAC5F9EB01K7GEG9W
A54: 2022-12-16 | D54: Distributor Shipment | E54: 8 | F54: 982.48 | G54: EUR | H54: 1370.48 | I54: EUR | J54: 33.40432 | K54: =J54/E54 -> 4.17554 | L54: =F54/E54 -> 122.81 | M54: EUR | N54: 33.40432 | O54: EUR | P54: 31DJDC7Q | Q54: B07W7MKLNS | S54: 5099206089860 | T54: LOGC8 | U54: L***8 | V54: 23 | W54: 2305300 | X54: 2305310 | Y54: Jaybird Vista 2 True Wireless Auricolari per lo sport Bluetooth con custodia di ricarica: ANC, Sport Fit, 24h di batteria, auricola riresistenti a tenuta stagna, chiamate di alta qualità - Grigio | AA54: consumer_electronics | AJ54: =P54&Q54 -> 31DJDC7QB07W7MKLNS
A55: 2022-12-28 | D55: Distributor Shipment | E55: 4 | F55: 335.56 | G55: EUR | H55: 540.96 | I55: EUR | J55: 11.40904 | K55: =J55/E55 -> 2.85226 | L55: =F55/E55 -> 83.89 | M55: EUR | N55: 11.40904 | O55: EUR | P55: 2F7Y5WIX | Q55: B07W4DHKTD | S55: 5099206090453 | T55: LOGC8 | U55: L***8 | V55: 147 | W55: 14700900 | X55: 14700933 | Y55: Logitech G PRO X SUPERLIGHT Mouse Gaming Wireless, Sensore HERO 25K, 25.600 DPI, Leggero con 63g, Progettato ‎per eSport, 5 Pulsanti Programmabili, PC/Mac/Laptop, Nero | AA55: pc | AJ55: =P55&Q55 -> 2F7Y5WIXB07W4DHKTD
A56: 2022-12-09 | D56: Distributor Shipment | E56: 0 | F56: 0 | G56: EUR | H56: 0 | I56: EUR | J56: 0 | K56: =J56/E56 -> #DIV/0! | L56: =F56/E56 -> #DIV/0! | M56: EUR | N56: 0 | O56: EUR | P56: 11Y5DH1J | Q56: B078MHS3SC | R56: 836213000274 | S56: 5099206084124 | T56: LOGC8 | U56: L***8 | V56: 267 | W56: 26704000 | X56: 26704200 | Y56: Blue Yeticaster Professional Broadcast Bundle con Microfono Yeti USB, Radius III Shockmount, Braccio Compass, Effetti Blue VO!CE per Registrazione, Streaming, Gaming, Podcasting - Nero | AA56: consumer_electronics | AJ56: =P56&Q56 -> 11Y5DH1JB078MHS3SC
A57: 2022-12-03 | D57: Distributor Shipment | E57: 0 | F57: 0 | G57: EUR | H57: 0 | I57: EUR | J57: 0 | K57: =J57/E57 -> #DIV/0! | L57: =F57/E57 -> #DIV/0! | M57: EUR | N57: 0 | O57: EUR | P57: 11Y5DH1J | Q57: B078MHS3SC | R57: 836213000274 | S57: 5099206084124 | T57: LOGC8 | U57: L***8 | V57: 267 | W57: 26704000 | X57: 26704200 | Y57: Blue Yeticaster Professional Broadcast Bundle con Microfono Yeti USB, Radius III Shockmount, Braccio Compass, Effetti Blue VO!CE per Registrazione, Streaming, Gaming, Podcasting - Nero | AA57: consumer_electronics | AJ57: =P57&Q57 -> 11Y5DH1JB078MHS3SC
A58: 2022-12-13 | D58: Distributor Shipment | E58: 1 | F58: 210.52 | G58: EUR | H58: 336.06 | I58: EUR | J58: 7.15768 | K58: =J58/E58 -> 7.15768 | L58: =F58/E58 -> 210.52 | M58: EUR | N58: 7.15768 | O58: EUR | P58: 23IZV8AJ | Q58: B013Y78YY4 | R58: 034722743600 | S58: 5099206059009 | T58: LOGC8 | U58: L***8 | V58: 147 | W58: 14700900 | X58: 14700939 | Y58: Volante da Corsa e Pedali Logitech G920 Driving Force, per Xbox One, Amp e PC, Spina UK | AA58: pc | AJ58: =P58&Q58 -> 23IZV8AJB013Y78YY4
A59: 2022-12-17 | D59: Distributor Shipment | E59: 8 | F59: 359.6 | G59: EUR | H59: 426.16 | I59: EUR | J59: 12.2264 | K59: =J59/E59 -> 1.5283 | L59: =F59/E59 -> 44.95 | M59: EUR | N59: 12.2264 | O59: EUR | P59: 2W68T8TO | Q59: B07W6HDNPG | S59: 5099206101548 | T59: LOGC8 | U59: L***8 | V59: 23 | W59: 14700900 | X59: 14700942 | Y59: ASTRO A10 Cuffie Gaming Cablate Gen 2, Cuffie da Gioco Over-Ear con Microfono Flip-to-Mute, Leggere e Resistenti, Driver 32 mm, Compatibile con PC/Mac, PS5, Xbox serie XIS, Switch,Mobile, Nero | AA59: consumer_electronics | AJ59: =P59&Q59 -> 2W68T8TOB07W6HDNPG
A60: 2022-12-06 | D60: Distributor Shipment | E60: 32 | F60: 412.16 | G60: EUR | H60: 671.68 | I60: EUR | J60: 14.01344 | K60: =J60/E60 -> 0.43792 | L60: =F60/E60 -> 12.88 | M60: EUR | N60: 14.01344 | O60: EUR | P60: 6451M4NB | Q60: B00745IE2K | R60: 097855083166 | S60: 0097855083166 | T60: LOGC8 | U60: L***8 | V60: 147 | W60: 14700900 | X60: 14700933 | Y60: Logitech M187 Mouse Wireless Tascabile Compatto, 2.4 GHz con Ricevitore USB, Rilevamento ‎Ottico 1000 DPI, 3 Pulsanti, PC/Mac/Laptop, Bianco | AA60: accessory | AJ60: =P60&Q60 -> 6451M4NBB00745IE2K
A61: 2022-12-29 | D61: Distributor Shipment | E61: 50 | F61: 526.5 | G61: EUR | H61: 619.5 | I61: EUR | J61: 17.901 | K61: =J61/E61 -> 0.35802 | L61: =F61/E61 -> 10.53 | M61: EUR | N61: 17.901 | O61: EUR | P61: 1PSIXGLT | Q61: B004APAH40 | S61: 5099206020764 | T61: LOGC8 | U61: L***8 | V61: 147 | W61: 14700900 | X61: 14700930 | Y61: Logitech K120 Tastiera con Cavo per Windows, USB Plug-and-Play, Dimensioni Standard, Resistente agli Schizzi, Barra Spaziatrice Curva, Compatibile con PC, Laptop, Layout Italiano QWERTY - Nero | AA61: pc | AJ61: =P61&Q61 -> 1PSIXGLTB004APAH40
A62: 2022-12-30 | D62: Distributor Shipment | E62: 124 | F62: 2943.76 | G62: EUR | H62: 4878.16 | I62: EUR | J62: 100.08784 | K62: =J62/E62 -> 0.80716 | L62: =F62/E62 -> 23.74 | M62: EUR | N62: 100.08784 | O62: EUR | P62: 4F3XMHTV | Q62: B07W6HBBMH | S62: 5099206104303 | T62: LOGC8 | U62: L***8 | V62: 147 | W62: 14700900 | X62: 14700933 | Y62: Logitech G G840 Gaming Mouse Pad XL, Ottimizzato per i Sensori da Gioco, Attrito Moderato, Antiscivolo, Accessori da Gioco per Mac e PC, 900 x 400 x 3 mm | AA62: consumer_electronics | AJ62: =P62&Q62 -> 4F3XMHTVB07W6HBBMH
A63: 2022-12-06 | D63: Distributor Shipment | E63: 4 | F63: 483.32 | G63: EUR | H63: 786.84 | I63: EUR | J63: 16.43288 | K63: =J63/E63 -> 4.10822 | L63: =F63/E63 -> 120.83 | M63: EUR | N63: 16.43288 | O63: EUR | P63: 5X1OU9ZG | Q63: B07W4DJF29 | S63: 5099206097520 | T63: LOGC8 | U63: L***8 | V63: 23 | W63: 2305300 | X63: 2305310 | Y63: Logitech G G735 Cuffie Gaming Wireless, Illuminazione RGB LIGHTSYNC Personalizzabile, LIGHTSPEED, Bluetooth, Aux 3,5 MM Compatibile con PC e Dispositivi Mobili, Microfono Staccabile - Bianco | AA63: consumer_electronics | AJ63: =P63&Q63 -> 5X1OU9ZGB07W4DJF29
A64: 2022-12-16 | D64: Distributor Shipment | E64: 80 | F64: 9281.6 | G64: EUR | H64: 13114.4 | I64: EUR | J64: 315.5744 | K64: =J64/E64 -> 3.94468 | L64: =F64/E64 -> 116.02 | M64: EUR | N64: 315.5744 | O64: EUR | P64: 2W68T8TO | Q64: B07W6HPP3R | S64: 5099206096134 | T64: LOGC8 | U64: L***8 | V64: 147 | W64: 14700900 | X64: 14700930 | Y64: Logitech Combo Touch Custodia con Tastiera per iPad Air (4 e 5 gen - 2020, 2022), Layout UK/US QWERTY - Grigio | AA64: pc | AJ64: =P64&Q64 -> 2W68T8TOB07W6HPP3R
A65: 2022-12-06 | D65: Distributor Shipment | E65: 204 | F65: 22495.08 | G65: EUR | H65: 38290.8 | I65: EUR | J65: 764.83272 | K65: =J65/E65 -> 3.74918 | L65: =F65/E65 -> 110.27 | M65: EUR | N65: 764.83272 | O65: EUR | P65: 7BEDNOMI | Q65: B07VTSZ63W | S65: 5099206080744 | T65: LOGC8 | U65: L***8 | V65: 147 | W65: 14700900 | X65: 14700939 | Y65: LOGITECH (ALEMÁN) G G815 TECLADO USB QWERTZ Negro | AA65: pc | AJ65: =P65&Q65 -> 7BEDNOMIB07VTSZ63W
A66: 2022-12-16 | D66: Distributor Shipment | E66: 40 | F66: 5336.8 | G66: EUR | H66: 7540.8 | I66: EUR | J66: 181.4512 | K66: =J66/E66 -> 4.53628 | L66: =F66/E66 -> 133.42 | M66: EUR | N66: 181.4512 | O66: EUR | P66: 31DJDC7Q | Q66: B07W6JNF81 | S66: 5099206095731 | T66: LOGC8 | U66: L***8 | V66: 147 | W66: 14700900 | X66: 14700930 | Y66: Logitech Combo Touch per iPad Pro da 12,9 pollici (5a, 6a gen - 2021, 2022) Custodia con tastiera, Supporto pieghevole, trackpad con tracciamento superficie, Smart Connector, Italiano QWERTY - Grigio | AA66: pc | AJ66: =P66&Q66 -> 31DJDC7QB07W6JNF81
A67: 2022-12-06 | D67: Distributor Shipment | E67: 2044 | F67: 149906.96 | G67: EUR | H67: 226168.6 | I67: EUR | J67: 5096.8366 | K67: =J67/E67 -> 2.49356 | L67: =F67/E67 -> 73.34 | M67: EUR | N67: 5096.8366 | O67: EUR | P67: 2F7Y5WIX | Q67: B07TLX61W7 | S67: 5099206085718 | T67: LOGC8 | U67: L***8 | V67: 147 | W67: 14700900 | X67: 14700939 | Y67: Logitech G PRO X Cuffia Gaming Cablata con Microfono Blue VO!CE, DTS Headphone:X 7.1 e Driver PRO-G da 50 mm, 7.1 Surround Pensato per Esport Gaming, per PC/PS/Xbox/Nintendo Switch, Nero | AA67: pc | AJ67: =P67&Q67 -> 2F7Y5WIXB07TLX61W7
A68: 2022-12-29 | D68: Distributor Shipment | E68: 440 | F68: 3348.4 | G68: EUR | H68: 4866.4 | I68: EUR | J68: 113.8456 | K68: =J68/E68 -> 0.25874 | L68: =F68/E68 -> 7.61 | M68: EUR | N68: 113.8456 | O68: EUR | P68: 7H9X1Z6S | Q68: B07W8LZB2L | S68: 5099206104242 | T68: LOGC8 | U68: L***8 | V68: 147 | W68: 14700900 | X68: 14700933 | Y68: Logitech M100 Mouse USB con Cavo, 3 Pulsanti, Tracciamento Ottico 1000 DPI, Ambidestro, Compatibile con PC, Mac, Laptop - Grigio | AA68: accessory | AJ68: =P68&Q68 -> 7H9X1Z6SB07W8LZB2L
A69: 2022-12-07 | D69: Distributor Shipment | E69: 100 | F69: 7334 | G69: EUR | H69: 11065 | I69: EUR | J69: 249.356 | K69: =J69/E69 -> 2.49356 | L69: =F69/E69 -> 73.34 | M69: EUR | N69: 249.356 | O69: EUR | P69: 2F7Y5WIX | Q69: B07TLX61W7 | S69: 5099206085718 | T69: LOGC8 | U69: L***8 | V69: 147 | W69: 14700900 | X69: 14700939 | Y69: Logitech G PRO X Cuffia Gaming Cablata con Microfono Blue VO!CE, DTS Headphone:X 7.1 e Driver PRO-G da 50 mm, 7.1 Surround Pensato per Esport Gaming, per PC/PS/Xbox/Nintendo Switch, Nero | AA69: pc | AJ69: =P69&Q69 -> 2F7Y5WIXB07TLX61W7
A70: 2022-12-06 | D70: Distributor Shipment | E70: 16 | F70: 590.88 | G70: EUR | H70: 983.52 | I70: EUR | J70: 20.08992 | K70: =J70/E70 -> 1.25562 | L70: =F70/E70 -> 36.93 | M70: EUR | N70: 20.08992 | O70: EUR | P70: 6451M4NB | Q70: B07CGNDZR3 | S70: 5099206077829 | T70: LOGC8 | U70: L***8 | V70: 147 | W70: 14700900 | X70: 14700933 | Y70: Logitech G305 LIGHTSPEED Mouse Gaming Wireless, Sensore 12K HERO, 12.000 DPI, Design Leggero, 6 Pulsanti Programmabili, Batteria 250 Ore, Memoria Integrata, PC/Laptop - Nero | AA70: accessory | AJ70: =P70&Q70 -> 6451M4NBB07CGNDZR3
A71: 2022-12-25 | D71: Distributor Shipment | E71: 0 | F71: 0 | G71: EUR | H71: 0 | I71: EUR | J71: 0 | K71: =J71/E71 -> #DIV/0! | L71: =F71/E71 -> #DIV/0! | M71: EUR | N71: 0 | O71: EUR | P71: 1X4DXX4T | Q71: B07SF1RCYF | S71: 5099206083943 | T71: LOGC8 | U71: L***8 | V71: 147 | W71: 14700900 | X71: 14700933 | Y71: Logitech G903 LIGHTSPEED Mouse Gaming Wireless, Sensore HERO 25K, Oltre 140 Ore con Batteria Ricaricabile e LIGHTSYNC RGB, POWERPLAY-compatibile, PC/Mac, Nero | AA71: pc | AJ71: =P71&Q71 -> 1X4DXX4TB07SF1RCYF
A72: 2022-12-22 | D72: Distributor Shipment | E72: 8 | F72: 774.64 | G72: EUR | H72: 918 | I72: EUR | J72: 26.33776 | K72: =J72/E72 -> 3.29222 | L72: =F72/E72 -> 96.83 | M72: EUR | N72: 26.33776 | O72: EUR | P72: 4LYATDUX | Q72: B002VA464S | R72: 733723132528 | S72: 0836213001950 | T72: LOGC8 | U72: L***8 | V72: 267 | W72: 26704000 | X72: 26704200 | Y72: Blue Yeti Microfono USB per Registrazione, Streaming, Gaming, Podcasting su PC e Mac, Mic a Condensatore per Laptop o Computer, Effetti Blue VO!CE, Stand Regolabile, Plug and Play - Argento | AA72: consumer_electronics | AJ72: =P72&Q72 -> 4LYATDUXB002VA464S
A73: 2022-12-07 | D73: Distributor Shipment | E73: 4 | F73: 147.72 | G73: EUR | H73: 245.88 | I73: EUR | J73: 5.02248 | K73: =J73/E73 -> 1.25562 | L73: =F73/E73 -> 36.93 | M73: EUR | N73: 5.02248 | O73: EUR | P73: 6451M4NB | Q73: B07CGNDZR3 | S73: 5099206077829 | T73: LOGC8 | U73: L***8 | V73: 147 | W73: 14700900 | X73: 14700933 | Y73: Logitech G305 LIGHTSPEED Mouse Gaming Wireless, Sensore 12K HERO, 12.000 DPI, Design Leggero, 6 Pulsanti Programmabili, Batteria 250 Ore, Memoria Integrata, PC/Laptop - Nero | AA73: accessory | AJ73: =P73&Q73 -> 6451M4NBB07CGNDZR3
A74: 2022-12-06 | D74: Distributor Shipment | E74: 24 | F74: 1284.24 | G74: EUR | H74: 1967.04 | I74: EUR | J74: 43.66416 | K74: =J74/E74 -> 1.81934 | L74: =F74/E74 -> 53.51 | M74: EUR | N74: 43.66416 | O74: EUR | P74: 6451M4NB | Q74: B07W6HLQ35 | S74: 5099206103771 | T74: LOGC8 | U74: L***8 | V74: 23 | W74: 2304100 | X74: 2304110 | Y74: Ultimate Ears WONDERBOOM 3, Altoparlante Portatile Wireless Bluetooth, Suono a 360 Gradi con Bassi Profondi, Impermeabile, Antipolvere IP67, Galleggiante, Portata 40 m - Blu | AA74: consumer_electronics | AJ74: =P74&Q74 -> 6451M4NBB07W6HLQ35
A75: 2022-12-14 | D75: Distributor Shipment | E75: 4 | F75: 467.56 | G75: EUR | H75: 586.88 | I75: EUR | J75: 15.89704 | K75: =J75/E75 -> 3.97426 | L75: =F75/E75 -> 116.89 | M75: EUR | N75: 15.89704 | O75: EUR | P75: 39TAD6PC | Q75: B07PMKHMFS | S75: 5099206084261 | T75: LOGC8 | U75: L***8 | V75: 147 | W75: 14700900 | X75: 14700939 | Y75: ASTRO Gaming A40 TR Cuffie Gaming Cablate, ASTRO Audio V2, Dolby ATMOS, Jack Audio 3,5 mm, Microfono Intercambiabile, per Xbox Series X|S/Xbox One/PC/Mac/Mobile/Plasystation, Nero/Rosso | AA75: pc | AJ75: =P75&Q75 -> 39TAD6PCB07PMKHMFS
A76: 2022-12-19 | D76: Distributor Shipment | E76: 4 | F76: 467.56 | G76: EUR | H76: 586.88 | I76: EUR | J76: 15.89704 | K76: =J76/E76 -> 3.97426 | L76: =F76/E76 -> 116.89 | M76: EUR | N76: 15.89704 | O76: EUR | P76: 39TAD6PC | Q76: B07PMKHMFS | S76: 5099206084261 | T76: LOGC8 | U76: L***8 | V76: 147 | W76: 14700900 | X76: 14700939 | Y76: ASTRO Gaming A40 TR Cuffie Gaming Cablate, ASTRO Audio V2, Dolby ATMOS, Jack Audio 3,5 mm, Microfono Intercambiabile, per Xbox Series X|S/Xbox One/PC/Mac/Mobile/Plasystation, Nero/Rosso | AA76: pc | AJ76: =P76&Q76 -> 39TAD6PCB07PMKHMFS
A77: 2022-12-04 | D77: Distributor Shipment | E77: 0 | F77: 0 | G77: EUR | H77: 0 | I77: EUR | J77: 0 | K77: =J77/E77 -> #DIV/0! | L77: =F77/E77 -> #DIV/0! | M77: EUR | N77: 0 | O77: EUR | P77: 4AP423UW | Q77: B00ZOZZM4U | S77: 5099206057340 | T77: LOGC8 | U77: L***8 | V77: 147 | W77: 14700900 | X77: 14700942 | Y77: Logitech H111 Cuffie Cablate per Computer, Stereo con Microfono, Cancellazione Rumore, ‎Jack Audio da 3.5 mm, PC/Mac/Laptop/Smartphone/Tablet, Nero | AA77: consumer_electronics | AJ77: =P77&Q77 -> 4AP423UWB00ZOZZM4U
A78: 2022-12-21 | D78: Distributor Shipment | E78: 112 | F78: 15896.16 | G78: EUR | H78: 32368 | I78: EUR | J78: 540.46944 | K78: =J78/E78 -> 4.82562 | L78: =F78/E78 -> 141.93 | M78: EUR | N78: 540.46944 | O78: EUR | P78: 8DUEXZHE | Q78: B07W6HMCF8 | S78: 5099206082700 | T78: LOGC8 | U78: L***8 | V78: 107 | W78: 2303100 | X78: 2303108 | Y78: Logitech G G915 Tastiera RF Wireless + Bluetooth QWERTZ Tedesco Nero | Z78: <p>Logitech G915. Fattore di forma tastiera: Standard. Stile tastiera: Dritto. Interfaccia dispositivo: RF Wireless + Bluetooth, Interruttore a chiave per tastiera: Interruttore a chiave meccanica, Struttura tastiera: QWERTZ, Utilizzo raccomandato: Giocare. Colore del prodotto: Nero</p> Requisiti di sistema<p> <br>-Sistema operativo Windows supportato: Windows 10,Windows 7,Windows 8<br> -Compatibilità sistema operativo Mac: Mac OS X 10.11 El Capitan,Mac OS X 10.12 Sierra,Mac OS X 10.13 High Sierra,Mac OS X 10.14 Mojave,Mac OS X 10.15 Catalina<br> -Sistema operativo mobile supportato: Android 10,Android 4.3,Android 4.4,Android 5.0,Android 5.1,Android 6.0,Android 7.0,Android 7.1,Android 8.0,Android 9.0,iOS 10.0,iOS 11.0,iOS 12<br> -Altri sistemi operativi supportati: Cromo<br> <br> Dimensioni e peso<p> <br>-Dimensioni tastiera (WxDxH): 475 x 150 x 22 mm<br> -Peso della tastiera: 1,02 kg<br> <br> Gestione energetica<p> <br>-Tipologia alimentazione: Batteria<br> <br> Tastiera<p> <br>-Utilizzo raccomandato: Giocare<br> -Interfaccia dispositivo: RF Wireless + Bluetooth<br> -Interruttore a chiave per tastiera: Interruttore a chiave meccanica<br> -Struttura tastiera: QWERTZ<br> -Linguaggio tastiera: Tedesco<br> -Dispositivo di puntatura: No<br> -Fattore di forma tastiera: Standard<br> -Tastiera numerica: Sì<br> -Tasti multimediali: Sì<br> -Distanza di pressione del tasto: 2,7 mm<br> -Forza di attuazione: 50 g<br> <br> Dati su imballaggio<p> <br>-Numero di prodotti inclusi: 1 pezzo(i)<br> -Ricevitore incluso: Sì<br> -interfaccia ricevitore senza fili: USB<br> <br> Design<p> <br>-Retroilluminazione: Sì<br> -Stile tastiera: Dritto<br> -Riposo del polso: No<br> -Colore del prodotto: Nero<br> <br> Mouse<p> <br>-Mouse incluso: No<br> <br> | AA78: pc | AJ78: =P78&Q78 -> 8DUEXZHEB07W6HMCF8
A79: 2022-12-13 | D79: Distributor Shipment | E79: 34 | F79: 7157.68 | G79: EUR | H79: 11426.04 | I79: EUR | J79: 243.36112 | K79: =J79/E79 -> 7.15768 | L79: =F79/E79 -> 210.52 | M79: EUR | N79: 243.36112 | O79: EUR | P79: 4A3KDTEZ | Q79: B013Y78YY4 | R79: 034722743600 | S79: 5099206059009 | T79: LOGC8 | U79: L***8 | V79: 147 | W79: 14700900 | X79: 14700939 | Y79: Volante da Corsa e Pedali Logitech G920 Driving Force, per Xbox One, Amp e PC, Spina UK | AA79: pc | AJ79: =P79&Q79 -> 4A3KDTEZB013Y78YY4
A80: 2022-12-16 | D80: Distributor Shipment | E80: 83 | F80: 18348.81 | G80: EUR | H80: 27892.98 | I80: EUR | J80: 623.85954 | K80: =J80/E80 -> 7.51638 | L80: =F80/E80 -> 221.07 | M80: EUR | N80: 623.85954 | O80: EUR | P80: 5KUAVFPZ | Q80: B00YUIM2J0 | S80: 5099206057302 | T80: LOGC8 | U80: L***8 | V80: 147 | W80: 14700900 | X80: 14700939 | Y80: Logitech G29 Driving Force Volante da Corsa con Pedali Regolabili, Ritorno di Forza Reale, Comandi Cambio in Acciaio Inossidabile, Volante in Pelle, Spina EU, PS5, PS4, PC, Mac - Nero | AA80: pc | AJ80: =P80&Q80 -> 5KUAVFPZB00YUIM2J0
A81: 2022-12-13 | D81: Distributor Shipment | E81: 16 | F81: 2545.44 | G81: EUR | H81: 3016.32 | I81: EUR | J81: 86.54496 | K81: =J81/E81 -> 5.40906 | L81: =F81/E81 -> 159.09 | M81: EUR | N81: 86.54496 | O81: EUR | P81: 1KW92RHQ | Q81: B078MHS3SC | R81: 836213000274 | S81: 5099206084124 | T81: LOGC8 | U81: L***8 | V81: 267 | W81: 26704000 | X81: 26704200 | Y81: Blue Yeticaster Professional Broadcast Bundle con Microfono Yeti USB, Radius III Shockmount, Braccio Compass, Effetti Blue VO!CE per Registrazione, Streaming, Gaming, Podcasting - Nero | AA81: consumer_electronics | AJ81: =P81&Q81 -> 1KW92RHQB078MHS3SC
A82: 2022-12-22 | D82: Distributor Shipment | E82: 10 | F82: 359.5 | G82: EUR | H82: 385.2 | I82: EUR | J82: 12.223 | K82: =J82/E82 -> 1.2223 | L82: =F82/E82 -> 35.95 | M82: EUR | N82: 12.223 | O82: EUR | P82: 4GF112AE | Q82: B07W5JKPJY | S82: 5099206097278 | T82: LOGC8 | U82: L***8 | V82: 147 | W82: 14700900 | X82: 14700933 | Y82: Logitech Signature M650 L for Business, Mouse wireless per mani grandi, Logi Bolt, Bluetooth, SmartWheel - Grigio | AA82: pc | AJ82: =P82&Q82 -> 4GF112AEB07W5JKPJY
A83: 2022-12-06 | D83: Distributor Shipment | E83: 36 | F83: 3020.04 | G83: EUR | H83: 4868.64 | I83: EUR | J83: 102.68136 | K83: =J83/E83 -> 2.85226 | L83: =F83/E83 -> 83.89 | M83: EUR | N83: 102.68136 | O83: EUR | P83: 2F7Y5WIX | Q83: B07W4DHKTD | S83: 5099206090453 | T83: LOGC8 | U83: L***8 | V83: 147 | W83: 14700900 | X83: 14700933 | Y83: Logitech G PRO X SUPERLIGHT Mouse Gaming Wireless, Sensore HERO 25K, 25.600 DPI, Leggero con 63g, Progettato ‎per eSport, 5 Pulsanti Programmabili, PC/Mac/Laptop, Nero | AA83: pc | AJ83: =P83&Q83 -> 2F7Y5WIXB07W4DHKTD
A84: 2022-12-30 | D84: Distributor Shipment | E84: 4 | F84: 211.04 | G84: EUR | H84: 340.96 | I84: EUR | J84: 7.17536 | K84: =J84/E84 -> 1.79384 | L84: =F84/E84 -> 52.76 | M84: EUR | N84: 7.17536 | O84: EUR | P84: 4F3XMHTV | Q84: B07W6JGH8Z | S84: 5099206094628 | T84: LOGC8 | U84: L***8 | V84: 63 | W84: 14700900 | X84: 14700939 | Y84: Logitech G Pro Vr Cuffia Wireless Gaming Per Oculus Quest 2, Per Oculus, Cavo Regolabile, Driver Audio Di Precisione Pro-G, Struttura Acciaio E Alluminio, Connessione Aux 3.5mm A Bassa Latenza Nero | AA84: game_video | AJ84: =P84&Q84 -> 4F3XMHTVB07W6JGH8Z
A85: 2022-12-06 | D85: Distributor Shipment | E85: 32 | F85: 936.96 | G85: EUR | H85: 936.96 | I85: EUR | J85: 31.85664 | K85: =J85/E85 -> 0.99552 | L85: =F85/E85 -> 29.28 | M85: EUR | N85: 31.85664 | O85: EUR | P85: 2F7Y5WIX | Q85: B00IRCDT7Y | S85: 5099206051805 | T85: LOGC8 | U85: L***8 | V85: 23 | W85: 2305800 | X85: 2305830 | Y85: Logitech Ricevitore Audio Bluetooth Wireless, ‎Pc/Mac/Smartphone/Tablet/Ricevitore Av, Uscite Audio 3.5 Mm E Rca Alle Casse Altoparlanti, ‎Nero, ‎5.71 x 5.08 x 2.23 cm; 175 grammi | AA85: pc | AJ85: =P85&Q85 -> 2F7Y5WIXB00IRCDT7Y
A86: 2022-12-16 | D86: Distributor Shipment | E86: 8 | F86: 324.8 | G86: EUR | H86: 472.08 | I86: EUR | J86: 11.0432 | K86: =J86/E86 -> 1.3804 | L86: =F86/E86 -> 40.6 | M86: EUR | N86: 11.0432 | O86: EUR | P86: 36BT7GGL | Q86: B07W7LNRN6 | S86: 5099206094130 | T86: LOGC8 | U86: L***8 | V86: 147 | W86: 14700900 | X86: 14700930 | Y86: Logitech Keys-To-Go Tastiera Bluetooth, Sottile e Leggera, per iPhone, iPad, Apple TV e tutti i dispositivi iOS, Layout Italiano QWERTY - Azul | AA86: pc | AJ86: =P86&Q86 -> 36BT7GGLB07W7LNRN6
A87: 2022-12-16 | D87: Distributor Shipment | E87: 4 | F87: 525.52 | G87: EUR | H87: 881.96 | I87: EUR | J87: 17.86768 | K87: =J87/E87 -> 4.46692 | L87: =F87/E87 -> 131.38 | M87: EUR | N87: 17.86768 | O87: EUR | P87: 56UO2L2I | Q87: B07W7LQDX7 | S87: 5099206088917 | T87: LOGII | U87: L***8 | V87: 147 | W87: 14700900 | X87: 14700930 | Y87: Logitech G915 TKL LIGHTSPEED Tastiera gaming meccanica wireless RGB senza tastierino numerico, opzioni di switch a profilo ribassato, LIGHTSYNC RGB, tecnologia wireless avanzata, Bluetooth - Nero | AA87: consumer_electronics | AJ87: =P87&Q87 -> 56UO2L2IB07W7LQDX7
A88: 2022-12-22 | D88: Distributor Shipment | E88: 8 | F88: 92.8 | G88: EUR | H88: 157.28 | I88: EUR | J88: 3.1552 | K88: =J88/E88 -> 0.3944 | L88: =F88/E88 -> 11.6 | M88: EUR | N88: 3.1552 | O88: EUR | P88: 8BG295LI | Q88: B01DIJIDKI | S88: 5099206064171 | T88: LOGC8 | U88: L***8 | V88: 147 | W88: 14700900 | X88: 14700939 | Y88: Logitech G240 Tappetino Mouse Gaming in Tessuto, Mouse Pad 340 x 280 mm, Spessore 1 mm, Attrito Moderato, Superficie Uniforme, Base in Gomma Stabile e Confortevole, Arrotolabile - Nero | AA88: accessory | AJ88: =P88&Q88 -> 8BG295LIB01DIJIDKI
A89: 2022-12-06 | D89: Distributor Shipment | E89: 50 | F89: 526.5 | G89: EUR | H89: 526.5 | I89: EUR | J89: 17.901 | K89: =J89/E89 -> 0.35802 | L89: =F89/E89 -> 10.53 | M89: EUR | N89: 17.901 | O89: EUR | P89: 2F7Y5WIX | Q89: B00544XFHC | R89: 097855075772 | S89: 0097855075772 | T89: LOGC8 | U89: L***8 | V89: 147 | W89: 14700900 | X89: 14700933 | Y89: Logitech M185 Mouse Wireless, 2,4 GHz con Mini Ricevitore USB, Durata Batteria di 12 Mesi, Tracciamento Ottico 1000 DPI, Ambidestro, Compatibile con PC, Mac, Laptop - Rosso | AA89: accessory | AJ89: =P89&Q89 -> 2F7Y5WIXB00544XFHC
A90: 2022-12-22 | D90: Distributor Shipment | E90: 48 | F90: 3313.44 | G90: EUR | H90: 5075.52 | I90: EUR | J90: 112.65696 | K90: =J90/E90 -> 2.34702 | L90: =F90/E90 -> 69.03 | M90: EUR | N90: 112.65696 | O90: EUR | P90: 5MWU8WTD | Q90: B07MM4V7NR | S90: 5099206082199 | T90: LOGC8 | U90: L***8 | V90: 147 | W90: 14700900 | X90: 14700942 | Y90: Logitech C920S HD Pro Webcam, Videochiamata Full HD 1080p/30fps, Audio Stereo ‎Chiaro, ‎Correzione Luce HD, Privacy Shutter, Per Skype, Zoom, FaceTime, Hangouts, ‎‎PC/Mac/Laptop/Tablet/XBox‎, Nero | AA90: pc | AJ90: =P90&Q90 -> 5MWU8WTDB07MM4V7NR
A91: 2022-12-16 | D91: Distributor Shipment | E91: 12 | F91: 538.08 | G91: EUR | H91: 865.44 | I91: EUR | J91: 18.29472 | K91: =J91/E91 -> 1.52456 | L91: =F91/E91 -> 44.84 | M91: EUR | N91: 18.29472 | O91: EUR | P91: 1PSIXGLT | Q91: B01LQTFOYK | S91: 5099206065970 | T91: LOGC8 | U91: L***8 | V91: 147 | W91: 14700700 | X91: 14700740 | Y91: Logitech G213 Prodigy Gaming Keyboard, RGB Lightsync Backlit Keys, Spill-Resistant, Customizable Keys, Dedicated Multi-Media Keys, QWERTY US International Layout, Nero | AA91: pc | AJ91: =P91&Q91 -> 1PSIXGLTB01LQTFOYK
A92: 2022-12-06 | D92: Distributor Shipment | E92: 40 | F92: 2933.6 | G92: EUR | H92: 4754 | I92: EUR | J92: 99.7424 | K92: =J92/E92 -> 2.49356 | L92: =F92/E92 -> 73.34 | M92: EUR | N92: 99.7424 | O92: EUR | P92: 3OB2IUIK | Q92: B073399S1L | S92: 5099206074576 | T92: LOGC8 | U92: L***8 | V92: 147 | W92: 14700900 | X92: 14700939 | Y92: Logitech G POWERPLAY Ricarica Wireless Tappetino Mouse, Tappetino per Mouse Gaming in Tessuto o Rigido, Mouse Pad Compatibile con G502 LIGHTSPEED, G PRO Wireless & SUPERLIGHT, G903, G703 | AA92: pc | AJ92: =P92&Q92 -> 3OB2IUIKB073399S1L
A93: 2022-12-16 | D93: Distributor Shipment | E93: 80 | F93: 3164.8 | G93: EUR | H93: 5245.6 | I93: EUR | J93: 107.6032 | K93: =J93/E93 -> 1.34504 | L93: =F93/E93 -> 39.56 | M93: EUR | N93: 107.6032 | O93: EUR | P93: 2TMBDXBK | Q93: B00L8VNQ88 | S93: 6298202673427 | T93: LOGC8 | U93: L***8 | V93: 147 | W93: 14700900 | X93: 14700933 | Y93: Logitech G402 Mouse Gaming Hyperion Fury, 4.000 DPI, Design Leggero, 8 Pulsanti Programmabili, Compatibile con PC/Mac/Laptop, PC/Mac, Nero | AA93: pc | AJ93: =P93&Q93 -> 2TMBDXBKB00L8VNQ88
A94: 2022-12-10 | D94: Distributor Shipment | E94: 4 | F94: 293.36 | G94: EUR | H94: 442.6 | I94: EUR | J94: 9.97424 | K94: =J94/E94 -> 2.49356 | L94: =F94/E94 -> 73.34 | M94: EUR | N94: 9.97424 | O94: EUR | P94: 2F7Y5WIX | Q94: B07TLX61W7 | S94: 5099206085718 | T94: LOGC8 | U94: L***8 | V94: 147 | W94: 14700900 | X94: 14700939 | Y94: Logitech G PRO X Cuffia Gaming Cablata con Microfono Blue VO!CE, DTS Headphone:X 7.1 e Driver PRO-G da 50 mm, 7.1 Surround Pensato per Esport Gaming, per PC/PS/Xbox/Nintendo Switch, Nero | AA94: pc | AJ94: =P94&Q94 -> 2F7Y5WIXB07TLX61W7
A95: 2022-12-29 | D95: Distributor Shipment | E95: 32 | F95: 656 | G95: EUR | H95: 996.48 | I95: EUR | J95: 22.304 | K95: =J95/E95 -> 0.697 | L95: =F95/E95 -> 20.5 | M95: EUR | N95: 22.304 | O95: EUR | P95: 243WWSUA | Q95: B007Z0YCEI | R95: 065030847599 | S95: 0065030847599 | T95: LOGC8 | U95: L***8 | V95: 147 | W95: 14700900 | X95: 14700930 | Y95: Logitech MK220 Combo Tastiera e Mouse Wireless Compatti per Windows, Layout ‎Portoghese QWERTY - Nero | AA95: consumer_electronics | AJ95: =P95&Q95 -> 243WWSUAB007Z0YCEI
A96: 2022-12-30 | D96: Distributor Shipment | E96: 4 | F96: 377.76 | G96: EUR | H96: 377.76 | I96: EUR | J96: 12.84384 | K96: =J96/E96 -> 3.21096 | L96: =F96/E96 -> 94.44 | M96: EUR | N96: 12.84384 | O96: EUR | P96: 2XSDZ5YG | Q96: B07W4DGCMW | S96: 5099206098589 | T96: PUU4N | U96: L***8 | V96: 147 | W96: 14700900 | X96: 14700954 | Y96: LOGITECH - GAMING DEVICES Tastiera da Gioco G713 - Bianco off - DEU - Centrale | AA96: pc | AJ96: =P96&Q96 -> 2XSDZ5YGB07W4DGCMW
A97: 2022-12-22 | D97: Distributor Shipment | E97: 152 | F97: 17635.04 | G97: EUR | H97: 24917.36 | I97: EUR | J97: 599.59136 | K97: =J97/E97 -> 3.94468 | L97: =F97/E97 -> 116.02 | M97: EUR | N97: 599.59136 | O97: EUR | P97: 5MWU8WTD | Q97: B07W6JKKBV | S97: 5099206095267 | T97: LOGC8 | U97: L***8 | V97: 147 | W97: 14700900 | X97: 14700930 | Y97: Logitech Combo Touch iPad Pro da 11 pollici (1a, 2a, 3a, 4a generazione - 2018, 2020, 2021, 2022) Custodia con tastiera - Tastiera retroilluminata staccabile - Italiano QWERTY - Grigio | AA97: pc | AJ97: =P97&Q97 -> 5MWU8WTDB07W6JKKBV
A98: 2022-12-22 | D98: Distributor Shipment | E98: 40 | F98: 1288.4 | G98: EUR | H98: 1934 | I98: EUR | J98: 43.8056 | K98: =J98/E98 -> 1.09514 | L98: =F98/E98 -> 32.21 | M98: EUR | N98: 43.8056 | O98: EUR | P98: 4LYATDUX | Q98: B07W6JM289 | S98: 5099206089037 | T98: LOGC8 | U98: L***8 | V98: 147 | W98: 14700900 | X98: 14700924 | Y98: Logitech K380 Tastiera, Layout Tedesco Qwertz, Bianco | AA98: pc | AJ98: =P98&Q98 -> 4LYATDUXB07W6JM289
A99: 2022-12-17 | D99: Distributor Shipment | E99: 16 | F99: 206.08 | G99: EUR | H99: 314.56 | I99: EUR | J99: 7.00672 | K99: =J99/E99 -> 0.43792 | L99: =F99/E99 -> 12.88 | M99: EUR | N99: 7.00672 | O99: EUR | P99: 36BT7GGL | Q99: B00745IE1Q | R99: 777304567385 | S99: 0182682407275 | T99: LOGC8 | U99: L***8 | V99: 147 | W99: 14700900 | X99: 14700933 | Y99: Logitech M187 Mouse Wireless Tascabile Compatto, 2.4 GHz con Ricevitore USB, Rilevamento ‎Ottico 1000 DPI, 3 Pulsanti, PC/Mac/Laptop, Nero | AA99: accessory | AJ99: =P99&Q99 -> 36BT7GGLB00745IE1Q
A100: 2022-12-29 | D100: Distributor Shipment | E100: 8 | F100: 187.36 | G100: EUR | H100: 288.48 | I100: EUR | J100: 6.37024 | K100: =J100/E100 -> 0.79628 | L100: =F100/E100 -> 23.42 | M100: EUR | N100: 6.37024 | O100: EUR | P100: 243WWSUA | Q100: B01DKGAQNG | S100: 5099206064485 | T100: LOGC8 | U100: L***8 | V100: 147 | W100: 14700900 | X100: 14700930 | Y100: Logitech MK235 Kit Mouse e tastiera, Layout QWERTZ, Nero | AA100: pc | AJ100: =P100&Q100 -> 243WWSUAB01DKGAQNG
...

Sheet Recon
A1: Claim Detail | E1: PO Detail | G1: Recon
A2: Concate | B2: Qty | C2: Invoice Price | D2: Invoice Rebate Amt | E2: Qty | F2: Price | G2: ASIN/PO Invalid | H2: Qty Check | I2: Claim Qty > PO Qty | J2: Price Variance
A3: 11FTNKDSB07W7LXYTR | B3: 8 | C3: =_xlfn.XLOOKUP(Recon!A3,[1]Backup!AJ:AJ,[1]Backup!L:L) -> 63.23 | D3: =_xlfn.XLOOKUP(Recon!A3,[1]Backup!AJ:AJ,[1]Backup!K:K) -> 2.14982 | E3: =SUMIF('[1]PO Report'!A:A,Recon!A3,'[1]PO Report'!P:P) -> 8 | F3: =VLOOKUP(A3,'[1]PO Report'!$A:$Z,15,0) -> 63.23 | H3: =B3-E3 -> 0 | J3: =C3-F3 -> 0
A4: 11Y5DH1JB07W6JPZBL | B4: 31 | C4: =_xlfn.XLOOKUP(Recon!A4,[1]Backup!AJ:AJ,[1]Backup!L:L) -> 240.27 | D4: =_xlfn.XLOOKUP(Recon!A4,[1]Backup!AJ:AJ,[1]Backup!K:K) -> 8.16918 | E4: =SUMIF('[1]PO Report'!A:A,Recon!A4,'[1]PO Report'!P:P) -> 31 | F4: =VLOOKUP(A4,'[1]PO Report'!$A:$Z,15,0) -> 240.27 | H4: =B4-E4 -> 0 | J4: =C4-F4 -> 0
A5: 13O47WAGB076CNH34R | B5: 4 | C5: =_xlfn.XLOOKUP(Recon!A5,[1]Backup!AJ:AJ,[1]Backup!L:L) -> 121.25 | D5: =_xlfn.XLOOKUP(Recon!A5,[1]Backup!AJ:AJ,[1]Backup!K:K) -> 4.1225 | E5: =SUMIF('[1]PO Report'!A:A,Recon!A5,'[1]PO Report'!P:P) -> 4 | F5: =VLOOKUP(A5,'[1]PO Report'!$A:$Z,15,0) -> 121.25 | H5: =B5-E5 -> 0 | J5: =C5-F5 -> 0
A6: 16QFG5EWB07W6JB7N7 | B6: 6 | C6: =_xlfn.XLOOKUP(Recon!A6,[1]Backup!AJ:AJ,[1]Backup!L:L) -> 210.52 | D6: =_xlfn.XLOOKUP(Recon!A6,[1]Backup!AJ:AJ,[1]Backup!K:K) -> 7.15768 | E6: =SUMIF('[1]PO Report'!A:A,Recon!A6,'[1]PO Report'!P:P) -> 6 | F6: =VLOOKUP(A6,'[1]PO Report'!$A:$Z,15,0) -> 210.52 | H6: =B6-E6 -> 0 | J6: =C6-F6 -> 0
A7: 172UACJHB01MCXJWD1 | B7: 66 | C7: =_xlfn.XLOOKUP(Recon!A7,[1]Backup!AJ:AJ,[1]Backup!L:L) -> 89.17 | D7: =_xlfn.XLOOKUP(Recon!A7,[1]Backup!AJ:AJ,[1]Backup!K:K) -> 3.03178 | E7: =SUMIF('[1]PO Report'!A:A,Recon!A7,'[1]PO Report'!P:P) -> 66 | F7: =VLOOKUP(A7,'[1]PO Report'!$A:$Z,15,0) -> 89.17 | H7: =B7-E7 -> 0 | J7: =C7-F7 -> 0
A8: 17D6YHERB0074486GA | B8: 4 | C8: =_xlfn.XLOOKUP(Recon!A8,[1]Backup!AJ:AJ,[1]Backup!L:L) -> 23.42 | D8: =_xlfn.XLOOKUP(Recon!A8,[1]Backup!AJ:AJ,[1]Backup!K:K) -> 0.79628 | E8: =SUMIF('[1]PO Report'!A:A,Recon!A8,'[1]PO Report'!P:P) -> 4 | F8: =VLOOKUP(A8,'[1]PO Report'!$A:$Z,15,0) -> 23.42 | H8: =B8-E8 -> 0 | J8: =C8-F8 -> 0
A9: 17D6YHERB00S67M430 | B9: 4 | C9: =_xlfn.XLOOKUP(Recon!A9,[1]Backup!AJ:AJ,[1]Backup!L:L) -> 35.13 | D9: =_xlfn.XLOOKUP(Recon!A9,[1]Backup!AJ:AJ,[1]Backup!K:K) -> 1.19442 | E9: =SUMIF('[1]PO Report'!A:A,Recon!A9,'[1]PO Report'!P:P) -> 4 | F9: =VLOOKUP(A9,'[1]PO Report'!$A:$Z,15,0) -> 35.13 | H9: =B9-E9 -> 0 | J9: =C9-F9 -> 0
A10: 17D6YHERB011N78DMA | B10: 3 | C10: =_xlfn.XLOOKUP(Recon!A10,[1]Backup!AJ:AJ,[1]Backup!L:L) -> 221.07 | D10: =_xlfn.XLOOKUP(Recon!A10,[1]Backup!AJ:AJ,[1]Backup!K:K) -> 7.51638 | E10: =SUMIF('[1]PO Report'!A:A,Recon!A10,'[1]PO Report'!P:P) -> 3 | F10: =VLOOKUP(A10,'[1]PO Report'!$A:$Z,15,0) -> 221.07 | H10: =B10-E10 -> 0 | J10: =C10-F10 -> 0
A11: 17D6YHERB01C4HCSOC | B11: 16 | C11: =_xlfn.XLOOKUP(Recon!A11,[1]Backup!AJ:AJ,[1]Backup!L:L) -> 23.42 | D11: =_xlfn.XLOOKUP(Recon!A11,[1]Backup!AJ:AJ,[1]Backup!K:K) -> 0.79628 | E11: =SUMIF('[1]PO Report'!A:A,Recon!A11,'[1]PO Report'!P:P) -> 16 | F11: =VLOOKUP(A11,'[1]PO Report'!$A:$Z,15,0) -> 23.42 | H11: =B11-E11 -> 0 | J11: =C11-F11 -> 0
A12: 17D6YHERB01MT5WL4M | B12: 24 | C12: =_xlfn.XLOOKUP(Recon!A12,[1]Backup!AJ:AJ,[1]Backup!L:L) -> 75.41 | D12: =_xlfn.XLOOKUP(Recon!A12,[1]Backup!AJ:AJ,[1]Backup!K:K) -> 2.56394 | E12: =SUMIF('[1]PO Report'!A:A,Recon!A12,'[1]PO Report'!P:P) -> 24 | F12: =VLOOKUP(A12,'[1]PO Report'!$A:$Z,15,0) -> 75.41 | H12: =B12-E12 -> 0 | J12: =C12-F12 -> 0
A13: 17D6YHERB01MT5WLHY | B13: 8 | C13: =_xlfn.XLOOKUP(Recon!A13,[1]Backup!AJ:AJ,[1]Backup!L:L) -> 75.41 | D13: =_xlfn.XLOOKUP(Recon!A13,[1]Backup!AJ:AJ,[1]Backup!K:K) -> 2.56394 | E13: =SUMIF('[1]PO Report'!A:A,Recon!A13,'[1]PO Report'!P:P) -> 8 | F13: =VLOOKUP(A13,'[1]PO Report'!$A:$Z,15,0) -> 75.41 | H13: =B13-E13 -> 0 | J13: =C13-F13 -> 0
A14: 17D6YHERB01MT5WMMG | B14: 24 | C14: =_xlfn.XLOOKUP(Recon!A14,[1]Backup!AJ:AJ,[1]Backup!L:L) -> 75.41 | D14: =_xlfn.XLOOKUP(Recon!A14,[1]Backup!AJ:AJ,[1]Backup!K:K) -> 2.56394 | E14: =SUMIF('[1]PO Report'!A:A,Recon!A14,'[1]PO Report'!P:P) -> 24 | F14: =VLOOKUP(A14,'[1]PO Report'!$A:$Z,15,0) -> 75.41 | H14: =B14-E14 -> 0 | J14: =C14-F14 -> 0
... A17: 17D6YHERB0797FYB3K | B17: 28 | C17: =_xlfn.XLOOKUP(Recon!A17,[1]Backup!AJ:AJ,[1]Backup!L:L) -> 43.92 | D17: =_xlfn.XLOOKUP(Recon!A17,[1]Backup!AJ:AJ,[1]Backup!K:K) -> 1.49328 | E17: =SUMIF('[1]PO Report'!A:A,Recon!A17,'[1]PO Report'!P:P) -> 28 | F17: =VLOOKUP(A17,'[1]PO Report'!$A:$Z,15,0) -> 43.92 | H17: =B17-E17 -> 0 | J17: =C17-F17 -> 0
A18: 17D6YHERB0797JRLQC | B18: 36 | C18: =_xlfn.XLOOKUP(Recon!A18,[1]Backup!AJ:AJ,[1]Backup!L:L) -> 43.92 | D18: =_xlfn.XLOOKUP(Recon!A18,[1]Backup!AJ:AJ,[1]Backup!K:K) -> 1.49328 | E18: =SUMIF('[1]PO Report'!A:A,Recon!A18,'[1]PO Report'!P:P) -> 32 | F18: =VLOOKUP(A18,'[1]PO Report'!$A:$Z,15,0) -> 43.92 | H18: =B18-E18 -> 4 | I18: =H18*D18 -> 5.97312 | J18: =C18-F18 -> 0
A19: 17D6YHERB0797LMGXH | B19: 4 | C19: =_xlfn.XLOOKUP(Recon!A19,[1]Backup!AJ:AJ,[1]Backup!L:L) -> 43.92 | D19: =_xlfn.XLOOKUP(Recon!A19,[1]Backup!AJ:AJ,[1]Backup!K:K) -> 1.49328 | E19: =SUMIF('[1]PO Report'!A:A,Recon!A19,'[1]PO Report'!P:P) -> 4 | F19: =VLOOKUP(A19,'[1]PO Report'!$A:$Z,15,0) -> 43.92 | H19: =B19-E19 -> 0 | J19: =C19-F19 -> 0
A20: 17D6YHERB079VVQS1R | B20: 2 | C20: =_xlfn.XLOOKUP(Recon!A20,[1]Backup!AJ:AJ,[1]Backup!L:L) -> 131.38 | D20: =_xlfn.XLOOKUP(Recon!A20,[1]Backup!AJ:AJ,[1]Backup!K:K) -> 4.46692 | E20: =SUMIF('[1]PO Report'!A:A,Recon!A20,'[1]PO Report'!P:P) -> 2 | F20: =VLOOKUP(A20,'[1]PO Report'!$A:$Z,15,0) -> 131.38 | H20: =B20-E20 -> 0 | J20: =C20-F20 -> 0
A21: 17D6YHERB07HZQT8JG | B21: 8 | C21: =_xlfn.XLOOKUP(Recon!A21,[1]Backup!AJ:AJ,[1]Backup!L:L) -> 73.34 | D21: =_xlfn.XLOOKUP(Recon!A21,[1]Backup!AJ:AJ,[1]Backup!K:K) -> 2.49356 | E21: =SUMIF('[1]PO Report'!A:A,Recon!A21,'[1]PO Report'!P:P) -> 8 | F21: =VLOOKUP(A21,'[1]PO Report'!$A:$Z,15,0) -> 73.34 | H21: =B21-E21 -> 0 | J21: =C21-F21 -> 0
A22: 17D6YHERB07W4DHXFT | B22: 56 | C22: =_xlfn.XLOOKUP(Recon!A22,[1]Backup!AJ:AJ,[1]Backup!L:L) -> 32.21 | D22: =_xlfn.XLOOKUP(Recon!A22,[1]Backup!AJ:AJ,[1]Backup!K:K) -> 1.09514 | E22: =SUMIF('[1]PO Report'!A:A,Recon!A22,'[1]PO Report'!P:P) -> 56 | F22: =VLOOKUP(A22,'[1]PO Report'!$A:$Z,15,0) -> 32.21 | H22: =B22-E22 -> 0 | J22: =C22-F22 -> 0
A23: 17D6YHERB07W6GVS5C | B23: 40 | C23: =_xlfn.XLOOKUP(Recon!A23,[1]Backup!AJ:AJ,[1]Backup!L:L) -> 44.84 | D23: =_xlfn.XLOOKUP(Recon!A23,[1]Backup!AJ:AJ,[1]Backup!K:K) -> 1.52456 | E23: =SUMIF('[1]PO Report'!A:A,Recon!A23,'[1]PO Report'!P:P) -> 40 | F23: =VLOOKUP(A23,'[1]PO Report'!$A:$Z,15,0) -> 44.84 | H23: =B23-E23 -> 0 | J23: =C23-F23 -> 0
A24: 17D6YHERB07W6JB7N7 | B24: 1 | C24: =_xlfn.XLOOKUP(Recon!A24,[1]Backup!AJ:AJ,[1]Backup!L:L) -> 210.52 | D24: =_xlfn.XLOOKUP(Recon!A24,[1]Backup!AJ:AJ,[1]Backup!K:K) -> 7.15768 | E24: =SUMIF('[1]PO Report'!A:A,Recon!A24,'[1]PO Report'!P:P) -> 1 | F24: =VLOOKUP(A24,'[1]PO Report'!$A:$Z,15,0) -> 210.52 | H24: =B24-E24 -> 0 | J24: =C24-F24 -> 0
A25: 17D6YHERB07W6JPVP3 | B25: 4 | C25: =_xlfn.XLOOKUP(Recon!A25,[1]Backup!AJ:AJ,[1]Backup!L:L) -> 74.84 | D25: =_xlfn.XLOOKUP(Recon!A25,[1]Backup!AJ:AJ,[1]Backup!K:K) -> 2.54456 | E25: =SUMIF('[1]PO Report'!A:A,Recon!A25,'[1]PO Report'!P:P) -> 4 | F25: =VLOOKUP(A25,'[1]PO Report'!$A:$Z,15,0) -> 74.84 | H25: =B25-E25 -> 0 | J25: =C25-F25 -> 0
A26: 17D6YHERB07W7K29YM | B26: 6 | C26: =_xlfn.XLOOKUP(Recon!A26,[1]Backup!AJ:AJ,[1]Backup!L:L) -> 29 | D26: =_xlfn.XLOOKUP(Recon!A26,[1]Backup!AJ:AJ,[1]Backup!K:K) -> 0.986 | E26: =SUMIF('[1]PO Report'!A:A,Recon!A26,'[1]PO Report'!P:P) -> 6 | F26: =VLOOKUP(A26,'[1]PO Report'!$A:$Z,15,0) -> 29 | H26: =B26-E26 -> 0 | J26: =C26-F26 -> 0
A27: 17D6YHERB07W7KFLBN | B27: 6 | C27: =_xlfn.XLOOKUP(Recon!A27,[1]Backup!AJ:AJ,[1]Backup!L:L) -> 29 | D27: =_xlfn.XLOOKUP(Recon!A27,[1]Backup!AJ:AJ,[1]Backup!K:K) -> 0.986 | E27: =SUMIF('[1]PO Report'!A:A,Recon!A27,'[1]PO Report'!P:P) -> 6 | F27: =VLOOKUP(A27,'[1]PO Report'!$A:$Z,15,0) -> 29 | H27: =B27-E27 -> 0 | J27: =C27-F27 -> 0
A28: 17D6YHERB07W7KNWK5 | B28: 8 | C28: =_xlfn.XLOOKUP(Recon!A28,[1]Backup!AJ:AJ,[1]Backup!L:L) -> 94.44 | D28: =_xlfn.XLOOKUP(Recon!A28,[1]Backup!AJ:AJ,[1]Backup!K:K) -> 3.21096 | E28: =SUMIF('[1]PO Report'!A:A,Recon!A28,'[1]PO Report'!P:P) -> 8 | F28: =VLOOKUP(A28,'[1]PO Report'!$A:$Z,15,0) -> 94.44 | H28: =B28-E28 -> 0 | J28: =C28-F28 -> 0
A29: 17D6YHERB07W7LF6F1 | B29: 480 | C29: =_xlfn.XLOOKUP(Recon!A29,[1]Backup!AJ:AJ,[1]Backup!L:L) -> 29 | D29: =_xlfn.XLOOKUP(Recon!A29,[1]Backup!AJ:AJ,[1]Backup!K:K) -> 0.986 | E29: =SUMIF('[1]PO Report'!A:A,Recon!A29,'[1]PO Report'!P:P) -> 480 | F29: =VLOOKUP(A29,'[1]PO Report'!$A:$Z,15,0) -> 29 | H29: =B29-E29 -> 0 | J29: =C29-F29 -> 0
A30: 17ETH86SB07W4DH5GL | B30: 4 | C30: =_xlfn.XLOOKUP(Recon!A30,[1]Backup!AJ:AJ,[1]Backup!L:L) -> 42.2 | D30: =_xlfn.XLOOKUP(Recon!A30,[1]Backup!AJ:AJ,[1]Backup!K:K) -> 1.4348 | E30: =SUMIF('[1]PO Report'!A:A,Recon!A30,'[1]PO Report'!P:P) -> 4 | F30: =VLOOKUP(A30,'[1]PO Report'!$A:$Z,15,0) -> 42.2 | H30: =B30-E30 -> 0 | J30: =C30-F30 -> 0
... A43: 1KW92RHQB078MHS3SC | B43: 16 | C43: =_xlfn.XLOOKUP(Recon!A43,[1]Backup!AJ:AJ,[1]Backup!L:L) -> 159.09 | D43: =_xlfn.XLOOKUP(Recon!A43,[1]Backup!AJ:AJ,[1]Backup!K:K) -> 5.40906 | E43: =SUMIF('[1]PO Report'!A:A,Recon!A43,'[1]PO Report'!P:P) -> 16 | F43: =VLOOKUP(A43,'[1]PO Report'!$A:$Z,15,0) -> 159.09 | H43: =B43-E43 -> 0 | J43: =C43-F43 -> 0
A44: 1KW92RHQB07VCS1895 | B44: 136 | C44: =_xlfn.XLOOKUP(Recon!A44,[1]Backup!AJ:AJ,[1]Backup!L:L) -> 35.13 | D44: =_xlfn.XLOOKUP(Recon!A44,[1]Backup!AJ:AJ,[1]Backup!K:K) -> 1.19442 | E44: =SUMIF('[1]PO Report'!A:A,Recon!A44,'[1]PO Report'!P:P) -> 132 | F44: =VLOOKUP(A44,'[1]PO Report'!$A:$Z,15,0) -> 35.13 | H44: =B44-E44 -> 4 | I44: =H44*D44 -> 4.77768 | J44: =C44-F44 -> 0
A45: 1KW92RHQB07W4DGQSX | B45: 32 | C45: =_xlfn.XLOOKUP(Recon!A45,[1]Backup!AJ:AJ,[1]Backup!L:L) -> 32.21 | D45: =_xlfn.XLOOKUP(Recon!A45,[1]Backup!AJ:AJ,[1]Backup!K:K) -> 1.09514 | E45: =SUMIF('[1]PO Report'!A:A,Recon!A45,'[1]PO Report'!P:P) -> 32 | F45: =VLOOKUP(A45,'[1]PO Report'!$A:$Z,15,0) -> 32.21 | H45: =B45-E45 -> 0 | J45: =C45-F45 -> 0
A46: 1KW92RHQB07W6JPZBL | B46: 90 | C46: =_xlfn.XLOOKUP(Recon!A46,[1]Backup!AJ:AJ,[1]Backup!L:L) -> 240.27 | D46: =_xlfn.XLOOKUP(Recon!A46,[1]Backup!AJ:AJ,[1]Backup!K:K) -> 8.16918 | E46: =SUMIF('[1]PO Report'!A:A,Recon!A46,'[1]PO Report'!P:P) -> 90 | F46: =VLOOKUP(A46,'[1]PO Report'!$A:$Z,15,0) -> 240.27 | H46: =B46-E46 -> 0 | J46: =C46-F46 -> 0
A47: 1KW92RHQB07W7LF6F1 | B47: 24 | C47: =_xlfn.XLOOKUP(Recon!A47,[1]Backup!AJ:AJ,[1]Backup!L:L) -> 29 | D47: =_xlfn.XLOOKUP(Recon!A47,[1]Backup!AJ:AJ,[1]Backup!K:K) -> 0.986 | E47: =SUMIF('[1]PO Report'!A:A,Recon!A47,'[1]PO Report'!P:P) -> 24 | F47: =VLOOKUP(A47,'[1]PO Report'!$A:$Z,15,0) -> 29 | H47: =B47-E47 -> 0 | J47: =C47-F47 -> 0
A48: 1KYIVKWCB004CM47VU | B48: 370 | C48: =_xlfn.XLOOKUP(Recon!A48,[1]Backup!AJ:AJ,[1]Backup!L:L) -> 17.56 | D48: =_xlfn.XLOOKUP(Recon!A48,[1]Backup!AJ:AJ,[1]Backup!K:K) -> 0.59704 | E48: =SUMIF('[1]PO Report'!A:A,Recon!A48,'[1]PO Report'!P:P) -> 370 | F48: =VLOOKUP(A48,'[1]PO Report'!$A:$Z,15,0) -> 17.56 | H48: =B48-E48 -> 0 | J48: =C48-F48 -> 0
A49: 1KYIVKWCB004PGM9KY | B49: 277 | C49: =_xlfn.XLOOKUP(Recon!A49,[1]Backup!AJ:AJ,[1]Backup!L:L) -> 248.87 | D49: =_xlfn.XLOOKUP(Recon!A49,[1]Backup!AJ:AJ,[1]Backup!K:K) -> 8.46158 | E49: =SUMIF('[1]PO Report'!A:A,Recon!A49,'[1]PO Report'!P:P) -> 277 | F49: =VLOOKUP(A49,'[1]PO Report'!$A:$Z,15,0) -> 248.87 | H49: =B49-E49 -> 0 | J49: =C49-F49 -> 0
A50: 1KYIVKWCB01DKGAQNG | B50: 8 | C50: =_xlfn.XLOOKUP(Recon!A50,[1]Backup!AJ:AJ,[1]Backup!L:L) -> 23.42 | D50: =_xlfn.XLOOKUP(Recon!A50,[1]Backup!AJ:AJ,[1]Backup!K:K) -> 0.79628 | E50: =SUMIF('[1]PO Report'!A:A,Recon!A50,'[1]PO Report'!P:P) -> 8 | F50: =VLOOKUP(A50,'[1]PO Report'!$A:$Z,15,0) -> 23.42 | H50: =B50-E50 -> 0 | J50: =C50-F50 -> 0
A51: 1KYIVKWCB01I252A34 | B51: 130 | C51: =_xlfn.XLOOKUP(Recon!A51,[1]Backup!AJ:AJ,[1]Backup!L:L) -> 16.39 | D51: =_xlfn.XLOOKUP(Recon!A51,[1]Backup!AJ:AJ,[1]Backup!K:K) -> 0.55726 | E51: =SUMIF('[1]PO Report'!A:A,Recon!A51,'[1]PO Report'!P:P) -> 130 | F51: =VLOOKUP(A51,'[1]PO Report'!$A:$Z,15,0) -> 16.39 | H51: =B51-E51 -> 0 | J51: =C51-F51 -> 0
A52: 1KYIVKWCB07W7KMK4Y | B52: 144 | C52: =_xlfn.XLOOKUP(Recon!A52,[1]Backup!AJ:AJ,[1]Backup!L:L) -> 69.03 | D52: =_xlfn.XLOOKUP(Recon!A52,[1]Backup!AJ:AJ,[1]Backup!K:K) -> 2.34702 | E52: =SUMIF('[1]PO Report'!A:A,Recon!A52,'[1]PO Report'!P:P) -> 144 | F52: =VLOOKUP(A52,'[1]PO Report'!$A:$Z,15,0) -> 69.03 | H52: =B52-E52 -> 0 | J52: =C52-F52 -> 0
A53: 1LQM129ZB00CJ5FP04 | B53: 8 | C53: =_xlfn.XLOOKUP(Recon!A53,[1]Backup!AJ:AJ,[1]Backup!L:L) -> 21.1 | D53: =_xlfn.XLOOKUP(Recon!A53,[1]Backup!AJ:AJ,[1]Backup!K:K) -> 0.7174 | E53: =SUMIF('[1]PO Report'!A:A,Recon!A53,'[1]PO Report'!P:P) -> 8 | F53: =VLOOKUP(A53,'[1]PO Report'!$A:$Z,15,0) -> 21.1 | H53: =B53-E53 -> 0 | J53: =C53-F53 -> 0
A54: 1LQM129ZB00ZOOKDU4 | B54: 44 | C54: =_xlfn.XLOOKUP(Recon!A54,[1]Backup!AJ:AJ,[1]Backup!L:L) -> 16.39 | D54: =_xlfn.XLOOKUP(Recon!A54,[1]Backup!AJ:AJ,[1]Backup!K:K) -> 0.55726 | E54: =SUMIF('[1]PO Report'!A:A,Recon!A54,'[1]PO Report'!P:P) -> 44 | F54: =VLOOKUP(A54,'[1]PO Report'!$A:$Z,15,0) -> 16.39 | H54: =B54-E54 -> 0 | J54: =C54-F54 -> 0
A55: 1LQM129ZB00ZOZZM4U | B55: 400 | C55: =_xlfn.XLOOKUP(Recon!A55,[1]Backup!AJ:AJ,[1]Backup!L:L) -> 12.88 | D55: =_xlfn.XLOOKUP(Recon!A55,[1]Backup!AJ:AJ,[1]Backup!K:K) -> 0.43792 | E55: =SUMIF('[1]PO Report'!A:A,Recon!A55,'[1]PO Report'!P:P) -> 400 | F55: =VLOOKUP(A55,'[1]PO Report'!$A:$Z,15,0) -> 12.88 | H55: =B55-E55 -> 0 | J55: =C55-F55 -> 0
A56: 1LQM129ZB07CGNP3RH | B56: 24 | C56: =_xlfn.XLOOKUP(Recon!A56,[1]Backup!AJ:AJ,[1]Backup!L:L) -> 36.93 | D56: =_xlfn.XLOOKUP(Recon!A56,[1]Backup!AJ:AJ,[1]Backup!K:K) -> 1.25562 | E56: =SUMIF('[1]PO Report'!A:A,Recon!A56,'[1]PO Report'!P:P) -> 28 | F56: =VLOOKUP(A56,'[1]PO Report'!$A:$Z,15,0) -> 36.93 | H56: =B56-E56 -> -4 | J56: =C56-F56 -> 0
... A96: 1VBBCE3CB07W6HDNPF | B96: 4 | C96: =_xlfn.XLOOKUP(Recon!A96,[1]Backup!AJ:AJ,[1]Backup!L:L) -> 44.95 | D96: =_xlfn.XLOOKUP(Recon!A96,[1]Backup!AJ:AJ,[1]Backup!K:K) -> 1.5283 | E96: =SUMIF('[1]PO Report'!A:A,Recon!A96,'[1]PO Report'!P:P) -> 4 | F96: =VLOOKUP(A96,'[1]PO Report'!$A:$Z,15,0) -> 44.95 | H96: =B96-E96 -> 0 | J96: =C96-F96 -> 0
A97: 1VBBCE3CB07W6HDNPG | B97: 12 | C97: =_xlfn.XLOOKUP(Recon!A97,[1]Backup!AJ:AJ,[1]Backup!L:L) -> 44.95 | D97: =_xlfn.XLOOKUP(Recon!A97,[1]Backup!AJ:AJ,[1]Backup!K:K) -> 1.5283 | E97: =SUMIF('[1]PO Report'!A:A,Recon!A97,'[1]PO Report'!P:P) -> 8 | F97: =VLOOKUP(A97,'[1]PO Report'!$A:$Z,15,0) -> 44.95 | H97: =B97-E97 -> 4 | I97: =H97*D97 -> 6.1132 | J97: =C97-F97 -> 0
A98: 1VRJRIPAB07W7M4MZP | B98: 8 | C98: =_xlfn.XLOOKUP(Recon!A98,[1]Backup!AJ:AJ,[1]Backup!L:L) -> 116.02 | D98: =_xlfn.XLOOKUP(Recon!A98,[1]Backup!AJ:AJ,[1]Backup!K:K) -> 3.94468 | E98: =SUMIF('[1]PO Report'!A:A,Recon!A98,'[1]PO Report'!P:P) -> 8 | F98: =VLOOKUP(A98,'[1]PO Report'!$A:$Z,15,0) -> 116.02 | H98: =B98-E98 -> 0 | J98: =C98-F98 -> 0
A99: 1X4DXX4TB004QTBPWI | B99: 40 | C99: =_xlfn.XLOOKUP(Recon!A99,[1]Backup!AJ:AJ,[1]Backup!L:L) -> 16.39 | D99: =_xlfn.XLOOKUP(Recon!A99,[1]Backup!AJ:AJ,[1]Backup!K:K) -> 0.55726 | E99: =SUMIF('[1]PO Report'!A:A,Recon!A99,'[1]PO Report'!P:P) -> 40 | F99: =VLOOKUP(A99,'[1]PO Report'!$A:$Z,15,0) -> 16.39 | H99: =B99-E99 -> 0 | J99: =C99-F99 -> 0
A100: 1X4DXX4TB004ZH0RHK | B100: 120 | C100: =_xlfn.XLOOKUP(Recon!A100,[1]Backup!AJ:AJ,[1]Backup!L:L) -> 29.28 | D100: =_xlfn.XLOOKUP(Recon!A100,[1]Backup!AJ:AJ,[1]Backup!K:K) -> 0.99552 | E100: =SUMIF('[1]PO Report'!A:A,Recon!A100,'[1]PO Report'!P:P) -> 120 | F100: =VLOOKUP(A100,'[1]PO Report'!$A:$Z,15,0) -> 29.28 | H100: =B100-E100 -> 0 | J100: =C100-F100 -> 0
A101: 1X4DXX4TB00544XFHC | B101: 30 | C101: =_xlfn.XLOOKUP(Recon!A101,[1]Backup!AJ:AJ,[1]Backup!L:L) -> 10.53 | D101: =_xlfn.XLOOKUP(Recon!A101,[1]Backup!AJ:AJ,[1]Backup!K:K) -> 0.35802 | E101: =SUMIF('[1]PO Report'!A:A,Recon!A101,'[1]PO Report'!P:P) -> 30 | F101: =VLOOKUP(A101,'[1]PO Report'!$A:$Z,15,0) -> 10.53 | H101: =B101-E101 -> 0 | J101: =C101-F101 -> 0
A102: 1X4DXX4TB006T02YRM | B102: 220 | C102: =_xlfn.XLOOKUP(Recon!A102,[1]Backup!AJ:AJ,[1]Backup!L:L) -> 23.42 | D102: =_xlfn.XLOOKUP(Recon!A102,[1]Backup!AJ:AJ,[1]Backup!K:K) -> 0.79628 | E102: =SUMIF('[1]PO Report'!A:A,Recon!A102,'[1]PO Report'!P:P) -> 220 | F102: =VLOOKUP(A102,'[1]PO Report'!$A:$Z,15,0) -> 23.42 | H102: =B102-E102 -> 0 | J102: =C102-F102 -> 0
A103: 1X4DXX4TB006ZLK9SQ | B103: 315 | C103: =_xlfn.XLOOKUP(Recon!A103,[1]Backup!AJ:AJ,[1]Backup!L:L) -> 20.5 | D103: =_xlfn.XLOOKUP(Recon!A103,[1]Backup!AJ:AJ,[1]Backup!K:K) -> 0.697 | E103: =SUMIF('[1]PO Report'!A:A,Recon!A103,'[1]PO Report'!P:P) -> 152 | F103: =VLOOKUP(A103,'[1]PO Report'!$A:$Z,15,0) -> 20.5 | H103: =B103-E103 -> 163 | I103: =H103*D103 -> 113.611 | J103: =C103-F103 -> 0
A104: 1X4DXX4TB00FSF2OSS | B104: 4 | C104: =_xlfn.XLOOKUP(Recon!A104,[1]Backup!AJ:AJ,[1]Backup!L:L) -> 29.28 | D104: =_xlfn.XLOOKUP(Recon!A104,[1]Backup!AJ:AJ,[1]Backup!K:K) -> 0.99552 | E104: =SUMIF('[1]PO Report'!A:A,Recon!A104,'[1]PO Report'!P:P) -> 4 | F104: =VLOOKUP(A104,'[1]PO Report'!$A:$Z,15,0) -> 29.28 | H104: =B104-E104 -> 0 | J104: =C104-F104 -> 0
A105: 1X4DXX4TB00PVWZH78 | B105: 200 | C105: =_xlfn.XLOOKUP(Recon!A105,[1]Backup!AJ:AJ,[1]Backup!L:L) -> 26.37 | D105: =_xlfn.XLOOKUP(Recon!A105,[1]Backup!AJ:AJ,[1]Backup!K:K) -> 0.89658 | E105: =SUMIF('[1]PO Report'!A:A,Recon!A105,'[1]PO Report'!P:P) -> 200 | F105: =VLOOKUP(A105,'[1]PO Report'!$A:$Z,15,0) -> 26.37 | H105: =B105-E105 -> 0 | J105: =C105-F105 -> 0
A106: 1X4DXX4TB0105Y2T5Y | B106: 4 | C106: =_xlfn.XLOOKUP(Recon!A106,[1]Backup!AJ:AJ,[1]Backup!L:L) -> 81.41 | D106: =_xlfn.XLOOKUP(Recon!A106,[1]Backup!AJ:AJ,[1]Backup!K:K) -> 2.76794 | E106: =SUMIF('[1]PO Report'!A:A,Recon!A106,'[1]PO Report'!P:P) -> 4 | F106: =VLOOKUP(A106,'[1]PO Report'!$A:$Z,15,0) -> 81.41 | H106: =B106-E106 -> 0 | J106: =C106-F106 -> 0
A107: 1X4DXX4TB010EPT2X6 | B107: 10 | C107: =_xlfn.XLOOKUP(Recon!A107,[1]Backup!AJ:AJ,[1]Backup!L:L) -> 32.21 | D107: =_xlfn.XLOOKUP(Recon!A107,[1]Backup!AJ:AJ,[1]Backup!K:K) -> 1.09514 | E107: =SUMIF('[1]PO Report'!A:A,Recon!A107,'[1]PO Report'!P:P) -> 10 | F107: =VLOOKUP(A107,'[1]PO Report'!$A:$Z,15,0) -> 32.21 | H107: =B107-E107 -> 0 | J107: =C107-F107 -> 0
A108: 1X4DXX4TB013SL1YXO | B108: 24 | C108: =_xlfn.XLOOKUP(Recon!A108,[1]Backup!AJ:AJ,[1]Backup!L:L) -> 32.21 | D108: =_xlfn.XLOOKUP(Recon!A108,[1]Backup!AJ:AJ,[1]Backup!K:K) -> 1.09514 | E108: =SUMIF('[1]PO Report'!A:A,Recon!A108,'[1]PO Report'!P:P) -> 24 | F108: =VLOOKUP(A108,'[1]PO Report'!$A:$Z,15,0) -> 32.21 | H108: =B108-E108 -> 0 | J108: =C108-F108 -> 0
A109: 1X4DXX4TB013SL1ZU6 | B109: 8 | C109: =_xlfn.XLOOKUP(Recon!A109,[1]Backup!AJ:AJ,[1]Backup!L:L) -> 32.21 | D109: =_xlfn.XLOOKUP(Recon!A109,[1]Backup!AJ:AJ,[1]Backup!K:K) -> 1.09514 | E109: =SUMIF('[1]PO Report'!A:A,Recon!A109,'[1]PO Report'!P:P) -> 8 | F109: =VLOOKUP(A109,'[1]PO Report'!$A:$Z,15,0) -> 32.21 | H109: =B109-E109 -> 0 | J109: =C109-F109 -> 0
A110: 1X4DXX4TB01K7GEFWK | B110: 80 | C110: =_xlfn.XLOOKUP(Recon!A110,[1]Backup!AJ:AJ,[1]Backup!L:L) -> 16.39 | D110: =_xlfn.XLOOKUP(Recon!A110,[1]Backup!AJ:AJ,[1]Backup!K:K) -> 0.55726 | E110: =SUMIF('[1]PO Report'!A:A,Recon!A110,'[1]PO Report'!P:P) -> 80 | F110: =VLOOKUP(A110,'[1]PO Report'!$A:$Z,15,0) -> 16.39 | H110: =B110-E110 -> 0 | J110: =C110-F110 -> 0
A111: 1X4DXX4TB01L6L52K4 | B111: 304 | C111: =_xlfn.XLOOKUP(Recon!A111,[1]Backup!AJ:AJ,[1]Backup!L:L) -> 75.41 | D111: =_xlfn.XLOOKUP(Recon!A111,[1]Backup!AJ:AJ,[1]Backup!K:K) -> 2.56394 | E111: =SUMIF('[1]PO Report'!A:A,Recon!A111,'[1]PO Report'!P:P) -> 304 | F111: =VLOOKUP(A111,'[1]PO Report'!$A:$Z,15,0) -> 75.41 | H111: =B111-E111 -> 0 | J111: =C111-F111 -> 0
A112: 1X4DXX4TB01M9EWQ2W | B112: 4 | C112: =_xlfn.XLOOKUP(Recon!A112,[1]Backup!AJ:AJ,[1]Backup!L:L) -> 94.44 | D112: =_xlfn.XLOOKUP(Recon!A112,[1]Backup!AJ:AJ,[1]Backup!K:K) -> 3.21096 | E112: =SUMIF('[1]PO Report'!A:A,Recon!A112,'[1]PO Report'!P:P) -> 4 | F112: =VLOOKUP(A112,'[1]PO Report'!$A:$Z,15,0) -> 94.44 | H112: =B112-E112 -> 0 | J112: =C112-F112 -> 0
A113: 1X4DXX4TB074N3HL5Q | B113: 16 | C113: =_xlfn.XLOOKUP(Recon!A113,[1]Backup!AJ:AJ,[1]Backup!L:L) -> 40.99 | D113: =_xlfn.XLOOKUP(Recon!A113,[1]Backup!AJ:AJ,[1]Backup!K:K) -> 1.39366 | E113: =SUMIF('[1]PO Report'!A:A,Recon!A113,'[1]PO Report'!P:P) -> 16 | F113: =VLOOKUP(A113,'[1]PO Report'!$A:$Z,15,0) -> 40.99 | H113: =B113-E113 -> 0 | J113: =C113-F113 -> 0
A114: 1X4DXX4TB07G6B2SGF | B114: 32 | C114: =_xlfn.XLOOKUP(Recon!A114,[1]Backup!AJ:AJ,[1]Backup!L:L) -> 21.4 | D114: =_xlfn.XLOOKUP(Recon!A114,[1]Backup!AJ:AJ,[1]Backup!K:K) -> 0.7276 | E114: =SUMIF('[1]PO Report'!A:A,Recon!A114,'[1]PO Report'!P:P) -> 32 | F114: =VLOOKUP(A114,'[1]PO Report'!$A:$Z,15,0) -> 21.4 | H114: =B114-E114 -> 0 | J114: =C114-F114 -> 0
A115: 1X4DXX4TB07MTY7N22 | B115: 44 | C115: =_xlfn.XLOOKUP(Recon!A115,[1]Backup!AJ:AJ,[1]Backup!L:L) -> 105 | D115: =_xlfn.XLOOKUP(Recon!A115,[1]Backup!AJ:AJ,[1]Backup!K:K) -> 3.57 | E115: =SUMIF('[1]PO Report'!A:A,Recon!A115,'[1]PO Report'!P:P) -> 44 | F115: =VLOOKUP(A115,'[1]PO Report'!$A:$Z,15,0) -> 105 | H115: =B115-E115 -> 0 | J115: =C115-F115 -> 0
... A126: 1X4DXX4TB07W5JKB92 | B126: 120 | C126: =_xlfn.XLOOKUP(Recon!A126,[1]Backup!AJ:AJ,[1]Backup!L:L) -> 131.38 | D126: =_xlfn.XLOOKUP(Recon!A126,[1]Backup!AJ:AJ,[1]Backup!K:K) -> 4.46692 | E126: =SUMIF('[1]PO Report'!A:A,Recon!A126,'[1]PO Report'!P:P) -> 120 | F126: =VLOOKUP(A126,'[1]PO Report'!$A:$Z,15,0) -> 131.38 | H126: =B126-E126 -> 0 | J126: =C126-F126 -> 0
A127: 1X4DXX4TB07W5JKNB9 | B127: 32 | C127: =_xlfn.XLOOKUP(Recon!A127,[1]Backup!AJ:AJ,[1]Backup!L:L) -> 69.03 | D127: =_xlfn.XLOOKUP(Recon!A127,[1]Backup!AJ:AJ,[1]Backup!K:K) -> 2.34702 | E127: =SUMIF('[1]PO Report'!A:A,Recon!A127,'[1]PO Report'!P:P) -> 28 | F127: =VLOOKUP(A127,'[1]PO Report'!$A:$Z,15,0) -> 69.03 | H127: =B127-E127 -> 4 | I127: =H127*D127 -> 9.38808 | J127: =C127-F127 -> 0
A128: 1X4DXX4TB07W5JKPFG | B128: 56 | C128: =_xlfn.XLOOKUP(Recon!A128,[1]Backup!AJ:AJ,[1]Backup!L:L) -> 32.21 | D128: =_xlfn.XLOOKUP(Recon!A128,[1]Backup!AJ:AJ,[1]Backup!K:K) -> 1.09514 | E128: =SUMIF('[1]PO Report'!A:A,Recon!A128,'[1]PO Report'!P:P) -> 56 | F128: =VLOOKUP(A128,'[1]PO Report'!$A:$Z,15,0) -> 32.21 | H128: =B128-E128 -> 0 | J128: =C128-F128 -> 0
A129: 1X4DXX4TB07W5JKWTH | B129: 16 | C129: =_xlfn.XLOOKUP(Recon!A129,[1]Backup!AJ:AJ,[1]Backup!L:L) -> 69.58 | D129: =_xlfn.XLOOKUP(Recon!A129,[1]Backup!AJ:AJ,[1]Backup!K:K) -> 2.36572 | E129: =SUMIF('[1]PO Report'!A:A,Recon!A129,'[1]PO Report'!P:P) -> 16 | F129: =VLOOKUP(A129,'[1]PO Report'!$A:$Z,15,0) -> 69.58 | H129: =B129-E129 -> 0 | J129: =C129-F129 -> 0
A130: 1X4DXX4TB07W6FNF6N | B130: 68 | C130: =_xlfn.XLOOKUP(Recon!A130,[1]Backup!AJ:AJ,[1]Backup!L:L) -> 75.41 | D130: =_xlfn.XLOOKUP(Recon!A130,[1]Backup!AJ:AJ,[1]Backup!K:K) -> 2.56394 | E130: =SUMIF('[1]PO Report'!A:A,Recon!A130,'[1]PO Report'!P:P) -> 68 | F130: =VLOOKUP(A130,'[1]PO Report'!$A:$Z,15,0) -> 75.41 | H130: =B130-E130 -> 0 | J130: =C130-F130 -> 0
A131: 1X4DXX4TB07W6GNXZF | B131: 32 | C131: =_xlfn.XLOOKUP(Recon!A131,[1]Backup!AJ:AJ,[1]Backup!L:L) -> 75.41 | D131: =_xlfn.XLOOKUP(Recon!A131,[1]Backup!AJ:AJ,[1]Backup!K:K) -> 2.56394 | E131: =SUMIF('[1]PO Report'!A:A,Recon!A131,'[1]PO Report'!P:P) -> 32 | F131: =VLOOKUP(A131,'[1]PO Report'!$A:$Z,15,0) -> 75.41 | H131: =B131-E131 -> 0 | J131: =C131-F131 -> 0
A132: 1X4DXX4TB07W6HLQ35 | B132: 40 | C132: =_xlfn.XLOOKUP(Recon!A132,[1]Backup!AJ:AJ,[1]Backup!L:L) -> 53.51 | D132: =_xlfn.XLOOKUP(Recon!A132,[1]Backup!AJ:AJ,[1]Backup!K:K) -> 1.81934 | E132: =SUMIF('[1]PO Report'!A:A,Recon!A132,'[1]PO Report'!P:P) -> 40 | F132: =VLOOKUP(A132,'[1]PO Report'!$A:$Z,15,0) -> 53.51 | H132: =B132-E132 -> 0 | J132: =C132-F132 -> 0
A133: 1X4DXX4TB07W6HSPY6 | B133: 24 | C133: =_xlfn.XLOOKUP(Recon!A133,[1]Backup!AJ:AJ,[1]Backup!L:L) -> 32.21 | D133: =_xlfn.XLOOKUP(Recon!A133,[1]Backup!AJ:AJ,[1]Backup!K:K) -> 1.09514 | E133: =SUMIF('[1]PO Report'!A:A,Recon!A133,'[1]PO Report'!P:P) -> 24 | F133: =VLOOKUP(A133,'[1]PO Report'!$A:$Z,15,0) -> 32.21 | H133: =B133-E133 -> 0 | J133: =C133-F133 -> 0
A134: 1X4DXX4TB07W6HYLB3 | B134: 4 | C134: =_xlfn.XLOOKUP(Recon!A134,[1]Backup!AJ:AJ,[1]Backup!L:L) -> 131.38 | D134: =_xlfn.XLOOKUP(Recon!A134,[1]Backup!AJ:AJ,[1]Backup!K:K) -> 4.46692 | E134: =SUMIF('[1]PO Report'!A:A,Recon!A134,'[1]PO Report'!P:P) -> 4 | F134: =VLOOKUP(A134,'[1]PO Report'!$A:$Z,15,0) -> 131.38 | H134: =B134-E134 -> 0 | J134: =C134-F134 -> 0
A135: 1X4DXX4TB07W6JM289 | B135: 32 | C135: =_xlfn.XLOOKUP(Recon!A135,[1]Backup!AJ:AJ,[1]Backup!L:L) -> 32.21 | D135: =_xlfn.XLOOKUP(Recon!A135,[1]Backup!AJ:AJ,[1]Backup!K:K) -> 1.09514 | E135: =SUMIF('[1]PO Report'!A:A,Recon!A135,'[1]PO Report'!P:P) -> 32 | F135: =VLOOKUP(A135,'[1]PO Report'!$A:$Z,15,0) -> 32.21 | H135: =B135-E135 -> 0 | J135: =C135-F135 -> 0
A136: 1X4DXX4TB07W6JNWP8 | B136: 10 | C136: =_xlfn.XLOOKUP(Recon!A136,[1]Backup!AJ:AJ,[1]Backup!L:L) -> 23.42 | D136: =_xlfn.XLOOKUP(Recon!A136,[1]Backup!AJ:AJ,[1]Backup!K:K) -> 0.79628 | E136: =SUMIF('[1]PO Report'!A:A,Recon!A136,'[1]PO Report'!P:P) -> 10 | F136: =VLOOKUP(A136,'[1]PO Report'!$A:$Z,15,0) -> 23.42 | H136: =B136-E136 -> 0 | J136: =C136-F136 -> 0
A137: 1X4DXX4TB07W6JP8N2 | B137: 4 | C137: =_xlfn.XLOOKUP(Recon!A137,[1]Backup!AJ:AJ,[1]Backup!L:L) -> 47.48 | D137: =_xlfn.XLOOKUP(Recon!A137,[1]Backup!AJ:AJ,[1]Backup!K:K) -> 1.61432 | E137: =SUMIF('[1]PO Report'!A:A,Recon!A137,'[1]PO Report'!P:P) -> 4 | F137: =VLOOKUP(A137,'[1]PO Report'!$A:$Z,15,0) -> 47.48 | H137: =B137-E137 -> 0 | J137: =C137-F137 -> 0
A138: 1X4DXX4TB07W7JYN4P | B138: 32 | C138: =_xlfn.XLOOKUP(Recon!A138,[1]Backup!AJ:AJ,[1]Backup!L:L) -> 69.03 | D138: =_xlfn.XLOOKUP(Recon!A138,[1]Backup!AJ:AJ,[1]Backup!K:K) -> 2.34702 | E138: =SUMIF('[1]PO Report'!A:A,Recon!A138,'[1]PO Report'!P:P) -> 32 | F138: =VLOOKUP(A138,'[1]PO Report'!$A:$Z,15,0) -> 69.03 | H138: =B138-E138 -> 0 | J138: =C138-F138 -> 0
A139: 1X4DXX4TB07W7JYP91 | B139: 10 | C139: =_xlfn.XLOOKUP(Recon!A139,[1]Backup!AJ:AJ,[1]Backup!L:L) -> 16.39 | D139: =_xlfn.XLOOKUP(Recon!A139,[1]Backup!AJ:AJ,[1]Backup!K:K) -> 0.55726 | E139: =SUMIF('[1]PO Report'!A:A,Recon!A139,'[1]PO Report'!P:P) -> 10 | F139: =VLOOKUP(A139,'[1]PO Report'!$A:$Z,15,0) -> 16.39 | H139: =B139-E139 -> 0 | J139: =C139-F139 -> 0
... A191: 2CLMXQWQB00CJ5FP04 | B191: 12 | C191: =_xlfn.XLOOKUP(Recon!A191,[1]Backup!AJ:AJ,[1]Backup!L:L) -> 21.1 | D191: =_xlfn.XLOOKUP(Recon!A191,[1]Backup!AJ:AJ,[1]Backup!K:K) -> 0.7174 | E191: =SUMIF('[1]PO Report'!A:A,Recon!A191,'[1]PO Report'!P:P) -> 12 | F191: =VLOOKUP(A191,'[1]PO Report'!$A:$Z,15,0) -> 21.1 | H191: =B191-E191 -> 0 | J191: =C191-F191 -> 0
A192: 2CLMXQWQB01BGBJ8Y0 | B192: 160 | C192: =_xlfn.XLOOKUP(Recon!A192,[1]Backup!AJ:AJ,[1]Backup!L:L) -> 23.42 | D192: =_xlfn.XLOOKUP(Recon!A192,[1]Backup!AJ:AJ,[1]Backup!K:K) -> 0.79628 | E192: =SUMIF('[1]PO Report'!A:A,Recon!A192,'[1]PO Report'!P:P) -> 144 | F192: =VLOOKUP(A192,'[1]PO Report'!$A:$Z,15,0) -> 23.42 | H192: =B192-E192 -> 16 | I192: =H192*D192 -> 12.74048 | J192: =C192-F192 -> 0
A193: 2CLMXQWQB01M3TTXMY | B193: 16 | C193: =_xlfn.XLOOKUP(Recon!A193,[1]Backup!AJ:AJ,[1]Backup!L:L) -> 83.89 | D193: =_xlfn.XLOOKUP(Recon!A193,[1]Backup!AJ:AJ,[1]Backup!K:K) -> 2.85226 | E193: =SUMIF('[1]PO Report'!A:A,Recon!A193,'[1]PO Report'!P:P) -> 16 | F193: =VLOOKUP(A193,'[1]PO Report'!$A:$Z,15,0) -> 83.89 | H193: =B193-E193 -> 0 | J193: =C193-F193 -> 0
A194: 2CLMXQWQB01MQ0GFUH | B194: 4 | C194: =_xlfn.XLOOKUP(Recon!A194,[1]Backup!AJ:AJ,[1]Backup!L:L) -> 44.84 | D194: =_xlfn.XLOOKUP(Recon!A194,[1]Backup!AJ:AJ,[1]Backup!K:K) -> 1.52456 | E194: =SUMIF('[1]PO Report'!A:A,Recon!A194,'[1]PO Report'!P:P) -> 4 | F194: =VLOOKUP(A194,'[1]PO Report'!$A:$Z,15,0) -> 44.84 | H194: =B194-E194 -> 0 | J194: =C194-F194 -> 0
A195: 2CLMXQWQB071ZFMC9Q | B195: 12 | C195: =_xlfn.XLOOKUP(Recon!A195,[1]Backup!AJ:AJ,[1]Backup!L:L) -> 66.66 | D195: =_xlfn.XLOOKUP(Recon!A195,[1]Backup!AJ:AJ,[1]Backup!K:K) -> 2.26644 | E195: =SUMIF('[1]PO Report'!A:A,Recon!A195,'[1]PO Report'!P:P) -> 12 | F195: =VLOOKUP(A195,'[1]PO Report'!$A:$Z,15,0) -> 66.66 | H195: =B195-E195 -> 0 | J195: =C195-F195 -> 0
A196: 2CLMXQWQB07CGNP3RH | B196: 56 | C196: =_xlfn.XLOOKUP(Recon!A196,[1]Backup!AJ:AJ,[1]Backup!L:L) -> 36.93 | D196: =_xlfn.XLOOKUP(Recon!A196,[1]Backup!AJ:AJ,[1]Backup!K:K) -> 1.25562 | E196: =SUMIF('[1]PO Report'!A:A,Recon!A196,'[1]PO Report'!P:P) -> 56 | F196: =VLOOKUP(A196,'[1]PO Report'!$A:$Z,15,0) -> 36.93 | H196: =B196-E196 -> 0 | J196: =C196-F196 -> 0
A197: 2CLMXQWQB07CGPZ3ZQ | B197: 272 | C197: =_xlfn.XLOOKUP(Recon!A197,[1]Backup!AJ:AJ,[1]Backup!L:L) -> 36.93 | D197: =_xlfn.XLOOKUP(Recon!A197,[1]Backup!AJ:AJ,[1]Backup!K:K) -> 1.25562 | E197: =SUMIF('[1]PO Report'!A:A,Recon!A197,'[1]PO Report'!P:P) -> 268 | F197: =VLOOKUP(A197,'[1]PO Report'!$A:$Z,15,0) -> 36.93 | H197: =B197-E197 -> 4 | I197: =H197*D197 -> 5.02248 | J197: =C197-F197 -> 0
A198: 2CLMXQWQB07QKC4WWD | B198: 24 | C198: =_xlfn.XLOOKUP(Recon!A198,[1]Backup!AJ:AJ,[1]Backup!L:L) -> 83.89 | D198: =_xlfn.XLOOKUP(Recon!A198,[1]Backup!AJ:AJ,[1]Backup!K:K) -> 2.85226 | E198: =SUMIF('[1]PO Report'!A:A,Recon!A198,'[1]PO Report'!P:P) -> 24 | F198: =VLOOKUP(A198,'[1]PO Report'!$A:$Z,15,0) -> 83.89 | H198: =B198-E198 -> 0 | J198: =C198-F198 -> 0
A199: 2CLMXQWQB07W4DHK3P | B199: 24 | C199: =_xlfn.XLOOKUP(Recon!A199,[1]Backup!AJ:AJ,[1]Backup!L:L) -> 21.1 | D199: =_xlfn.XLOOKUP(Recon!A199,[1]Backup!AJ:AJ,[1]Backup!K:K) -> 0.7174 | E199: =SUMIF('[1]PO Report'!A:A,Recon!A199,'[1]PO Report'!P:P) -> 24 | F199: =VLOOKUP(A199,'[1]PO Report'!$A:$Z,15,0) -> 21.1 | H199: =B199-E199 -> 0 | J199: =C199-F199 -> 0
A200: 2CLMXQWQB07W6H83LD | B200: 4 | C200: =_xlfn.XLOOKUP(Recon!A200,[1]Backup!AJ:AJ,[1]Backup!L:L) -> 18.46 | D200: =_xlfn.XLOOKUP(Recon!A200,[1]Backup!AJ:AJ,[1]Backup!K:K) -> 0.62764 | E200: =SUMIF('[1]PO Report'!A:A,Recon!A200,'[1]PO Report'!P:P) -> 4 | F200: =VLOOKUP(A200,'[1]PO Report'!$A:$Z,15,0) -> 18.46 | H200: =B200-E200 -> 0 | J200: =C200-F200 -> 0
A201: 2CLMXQWQB07W6HPP3R | B201: 48 | C201: =_xlfn.XLOOKUP(Recon!A201,[1]Backup!AJ:AJ,[1]Backup!L:L) -> 116.02 | D201: =_xlfn.XLOOKUP(Recon!A201,[1]Backup!AJ:AJ,[1]Backup!K:K) -> 3.94468 | E201: =SUMIF('[1]PO Report'!A:A,Recon!A201,'[1]PO Report'!P:P) -> 48 | F201: =VLOOKUP(A201,'[1]PO Report'!$A:$Z,15,0) -> 116.02 | H201: =B201-E201 -> 0 | J201: =C201-F201 -> 0
A202: 2CLMXQWQB07W6JGH8Z | B202: 4 | C202: =_xlfn.XLOOKUP(Recon!A202,[1]Backup!AJ:AJ,[1]Backup!L:L) -> 52.76 | D202: =_xlfn.XLOOKUP(Recon!A202,[1]Backup!AJ:AJ,[1]Backup!K:K) -> 1.79384 | E202: =SUMIF('[1]PO Report'!A:A,Recon!A202,'[1]PO Report'!P:P) -> 4 | F202: =VLOOKUP(A202,'[1]PO Report'!$A:$Z,15,0) -> 52.76 | H202: =B202-E202 -> 0 | J202: =C202-F202 -> 0
A203: 2CLMXQWQB07W6JPM9P | B203: 60 | C203: =_xlfn.XLOOKUP(Recon!A203,[1]Backup!AJ:AJ,[1]Backup!L:L) -> 6.32 | D203: =_xlfn.XLOOKUP(Recon!A203,[1]Backup!AJ:AJ,[1]Backup!K:K) -> 0.21488 | E203: =SUMIF('[1]PO Report'!A:A,Recon!A203,'[1]PO Report'!P:P) -> 60 | F203: =VLOOKUP(A203,'[1]PO Report'!$A:$Z,15,0) -> 6.32 | H203: =B203-E203 -> 0 | J203: =C203-F203 -> 0
A204: 2CLMXQWQB07W6JPVPF | B204: 16 | C204: =_xlfn.XLOOKUP(Recon!A204,[1]Backup!AJ:AJ,[1]Backup!L:L) -> 23.74 | D204: =_xlfn.XLOOKUP(Recon!A204,[1]Backup!AJ:AJ,[1]Backup!K:K) -> 0.80716 | E204: =SUMIF('[1]PO Report'!A:A,Recon!A204,'[1]PO Report'!P:P) -> 16 | F204: =VLOOKUP(A204,'[1]PO Report'!$A:$Z,15,0) -> 23.74 | H204: =B204-E204 -> 0 | J204: =C204-F204 -> 0
A205: 2CLMXQWQB07W7K29YK | B205: 24 | C205: =_xlfn.XLOOKUP(Recon!A205,[1]Backup!AJ:AJ,[1]Backup!L:L) -> 11.6 | D205: =_xlfn.XLOOKUP(Recon!A205,[1]Backup!AJ:AJ,[1]Backup!K:K) -> 0.3944 | E205: =SUMIF('[1]PO Report'!A:A,Recon!A205,'[1]PO Report'!P:P) -> 24 | F205: =VLOOKUP(A205,'[1]PO Report'!$A:$Z,15,0) -> 11.6 | H205: =B205-E205 -> 0 | J205: =C205-F205 -> 0
A206: 2CLMXQWQB07W7LNTMC | B206: 24 | C206: =_xlfn.XLOOKUP(Recon!A206,[1]Backup!AJ:AJ,[1]Backup!L:L) -> 11.6 | D206: =_xlfn.XLOOKUP(Recon!A206,[1]Backup!AJ:AJ,[1]Backup!K:K) -> 0.3944 | E206: =SUMIF('[1]PO Report'!A:A,Recon!A206,'[1]PO Report'!P:P) -> 24 | F206: =VLOOKUP(A206,'[1]PO Report'!$A:$Z,15,0) -> 11.6 | H206: =B206-E206 -> 0 | J206: =C206-F206 -> 0
A207: 2DDMOF4WB07W7L3HJP | B207: 12 | C207: =_xlfn.XLOOKUP(Recon!A207,[1]Backup!AJ:AJ,[1]Backup!L:L) -> 55.1 | D207: =_xlfn.XLOOKUP(Recon!A207,[1]Backup!AJ:AJ,[1]Backup!K:K) -> 1.8734 | E207: =SUMIF('[1]PO Report'!A:A,Recon!A207,'[1]PO Report'!P:P) -> 12 | F207: =VLOOKUP(A207,'[1]PO Report'!$A:$Z,15,0) -> 55.1 | H207: =B207-E207 -> 0 | J207: =C207-F207 -> 0
A208: 2DDMOF4WB07W7LTX74 | B208: 8 | C208: =_xlfn.XLOOKUP(Recon!A208,[1]Backup!AJ:AJ,[1]Backup!L:L) -> 104.41 | D208: =_xlfn.XLOOKUP(Recon!A208,[1]Backup!AJ:AJ,[1]Backup!K:K) -> 3.54994 | E208: =SUMIF('[1]PO Report'!A:A,Recon!A208,'[1]PO Report'!P:P) -> 8 | F208: =VLOOKUP(A208,'[1]PO Report'!$A:$Z,15,0) -> 104.41 | H208: =B208-E208 -> 0 | J208: =C208-F208 -> 0
A209: 2F7Y5WIXB000EOPQ7E | B209: 8 | C209: =_xlfn.XLOOKUP(Recon!A209,[1]Backup!AJ:AJ,[1]Backup!L:L) -> 58.79 | D209: =_xlfn.XLOOKUP(Recon!A209,[1]Backup!AJ:AJ,[1]Backup!K:K) -> 1.99886 | E209: =SUMIF('[1]PO Report'!A:A,Recon!A209,'[1]PO Report'!P:P) -> 8 | F209: =VLOOKUP(A209,'[1]PO Report'!$A:$Z,15,0) -> 58.79 | H209: =B209-E209 -> 0 | J209: =C209-F209 -> 0
... A221: 2F7Y5WIXB07TLX61W7 | B221: 2148 | C221: =_xlfn.XLOOKUP(Recon!A221,[1]Backup!AJ:AJ,[1]Backup!L:L) -> 73.34 | D221: =_xlfn.XLOOKUP(Recon!A221,[1]Backup!AJ:AJ,[1]Backup!K:K) -> 2.49356 | E221: =SUMIF('[1]PO Report'!A:A,Recon!A221,'[1]PO Report'!P:P) -> 2148 | F221: =VLOOKUP(A221,'[1]PO Report'!$A:$Z,15,0) -> 73.34 | H221: =B221-E221 -> 0 | J221: =C221-F221 -> 0
A222: 2F7Y5WIXB07W4DHKTD | B222: 40 | C222: =_xlfn.XLOOKUP(Recon!A222,[1]Backup!AJ:AJ,[1]Backup!L:L) -> 83.89 | D222: =_xlfn.XLOOKUP(Recon!A222,[1]Backup!AJ:AJ,[1]Backup!K:K) -> 2.85226 | E222: =SUMIF('[1]PO Report'!A:A,Recon!A222,'[1]PO Report'!P:P) -> 36 | F222: =VLOOKUP(A222,'[1]PO Report'!$A:$Z,15,0) -> 83.89 | H222: =B222-E222 -> 4 | I222: =H222*D222 -> 11.40904 | J222: =C222-F222 -> 0
A223: 2F7Y5WIXB07W4DHZLS | B223: 8 | C223: =_xlfn.XLOOKUP(Recon!A223,[1]Backup!AJ:AJ,[1]Backup!L:L) -> 40.6 | D223: =_xlfn.XLOOKUP(Recon!A223,[1]Backup!AJ:AJ,[1]Backup!K:K) -> 1.3804 | E223: =SUMIF('[1]PO Report'!A:A,Recon!A223,'[1]PO Report'!P:P) -> 8 | F223: =VLOOKUP(A223,'[1]PO Report'!$A:$Z,15,0) -> 40.6 | H223: =B223-E223 -> 0 | J223: =C223-F223 -> 0
A224: 2F7Y5WIXB07W4DJ16Z | B224: 80 | C224: =_xlfn.XLOOKUP(Recon!A224,[1]Backup!AJ:AJ,[1]Backup!L:L) -> 16.39 | D224: =_xlfn.XLOOKUP(Recon!A224,[1]Backup!AJ:AJ,[1]Backup!K:K) -> 0.55726 | E224: =SUMIF('[1]PO Report'!A:A,Recon!A224,'[1]PO Report'!P:P) -> 80 | F224: =VLOOKUP(A224,'[1]PO Report'!$A:$Z,15,0) -> 16.39 | H224: =B224-E224 -> 0 | J224: =C224-F224 -> 0
A225: 2F7Y5WIXB07W5JHF5D | B225: 40 | C225: =_xlfn.XLOOKUP(Recon!A225,[1]Backup!AJ:AJ,[1]Backup!L:L) -> 32.21 | D225: =_xlfn.XLOOKUP(Recon!A225,[1]Backup!AJ:AJ,[1]Backup!K:K) -> 1.09514 | E225: =SUMIF('[1]PO Report'!A:A,Recon!A225,'[1]PO Report'!P:P) -> 40 | F225: =VLOOKUP(A225,'[1]PO Report'!$A:$Z,15,0) -> 32.21 | H225: =B225-E225 -> 0 | J225: =C225-F225 -> 0
...

Sheet Dispute Summary
A2: Dispute Summary
A3: ASIN/PO combo Invalid | B3: #REF!
A4: Claim Qty > PO Qty | B4: 527.79764
B5: #REF!
A9: ASIN/PO combo Invalid
A10: PO | B10: ASIN | C10: QTY | D10: Rebate | E10: Total
A11: 7RAC5F9E | B11: B07TLX61W7 | C11: 4 | D11: 0.79628 | E11: #REF!
E12: #REF!
A14: Claim Qty > PO Qty
A15: PO | B15: ASIN | C15: PO Qty | D15: Claim QTY | E15: Over Claimed Qty | F15: Rebate Amt | G15: Total Over claim
A16: 17D6YHER | B16: B0797JRLQC | C16: 32 | D16: 36 | E16: 4 | F16: 1.49328 | G16: 5.97312
A17: 1KW92RHQ | B17: B07VCS1895 | C17: 132 | D17: 136 | E17: 4 | F17: 1.19442 | G17: 4.77768
A18: 1VBBCE3C | B18: B07W6HDNPG | C18: 8 | D18: 12 | E18: 4 | F18: 1.5283 | G18: 6.1132
A19: 1X4DXX4T | B19: B006ZLK9SQ | C19: 152 | D19: 315 | E19: 163 | F19: 0.697 | G19: 113.611
A20: 1X4DXX4T | B20: B07W5JKNB9 | C20: 28 | D20: 32 | E20: 4 | F20: 2.34702 | G20: 9.38808
A21: 2CLMXQWQ | B21: B01BGBJ8Y0 | C21: 144 | D21: 160 | E21: 16 | F21: 0.79628 | G21: 12.74048
A22: 2CLMXQWQ | B22: B07CGPZ3ZQ | C22: 268 | D22: 272 | E22: 4 | F22: 1.25562 | G22: 5.02248
A23: 2F7Y5WIX | B23: B07W4DHKTD | C23: 36 | D23: 40 | E23: 4 | F23: 2.85226 | G23: 11.40904
A24: 2LZI7R4T | B24: B077BT728N | C24: 2820 | D24: 2870 | E24: 50 | F24: 0.55726 | G24: 27.863
A25: 2M7QFTCO | B25: B07W6JKH1B | C25: 8 | D25: 16 | E25: 8 | F25: 1.09514 | G25: 8.76112
A26: 2R6FMUZD | B26: B006A2Q81M | C26: 8 | D26: 12 | E26: 4 | F26: 2.14982 | G26: 8.59928
A27: 2R6FMUZD | B27: B07W5JKFQC | C27: 80 | D27: 84 | E27: 4 | F27: 0.80716 | G27: 3.22864
... A55: 8SGS6BFX | B55: B00IRCDT7Y | C55: 844 | D55: 852 | E55: 8 | F55: 0.99552 | G55: 7.96416
G56: 527.79764
